{"after": null, "whitelist_status": "all_ads", "modhash": "", "dist": null, "children": [{"kind": "t1", "data": {"body": "John Titor, you've changed maaan.", "subreddit_id": "t5_2s3qj", "approved_at_utc": null, "ups": 2, "mod_reason_by": null, "banned_by": null, "removal_reason": null, "link_id": "t3_86a4c7", "likes": null, "no_follow": true, "replies": {"kind": "Listing", "data": {"after": null, "whitelist_status": "all_ads", "modhash": "", "dist": null, "children": [{"kind": "t1", "data": {"subreddit_id": "t5_2s3qj", "approved_at_utc": null, "ups": 2, "mod_reason_by": null, "banned_by": null, "removal_reason": null, "link_id": "t3_86a4c7", "likes": null, "no_follow": true, "replies": "", "user_reports": [], "saved": false, "id": "dw3rzi4", "banned_at_utc": null, "mod_reason_title": null, "gilded": 0, "archived": false, "report_reasons": null, "author": "dezmd", "can_mod_post": false, "send_replies": true, "parent_id": "t1_dw3lduz", "score": 2, "approved_by": null, "downs": 0, "body": "Obviously the first timeline Jon Titor changed more than he planned.  ", "edited": false, "author_flair_css_class": null, "collapsed": false, "is_submitter": false, "collapsed_reason": null, "body_html": "&lt;div class=\"md\"&gt;&lt;p&gt;Obviously the first timeline Jon Titor changed more than he planned.  &lt;/p&gt;\n&lt;/div&gt;", "subreddit_type": "public", "can_gild": true, "subreddit": "Bitcoin", "name": "t1_dw3rzi4", "score_hidden": false, "permalink": "/r/Bitcoin/comments/86a4c7/countermessage_from_the_future/dw3rzi4/", "num_reports": null, "stickied": false, "created": 1521756500.0, "author_flair_text": null, "created_utc": 1521727700.0, "subreddit_name_prefixed": "r/Bitcoin", "controversiality": 0, "depth": 1, "mod_reports": [], "mod_note": null, "distinguished": null}}], "before": null}}, "user_reports": [], "saved": false, "id": "dw3lduz", "banned_at_utc": null, "mod_reason_title": null, "gilded": 0, "archived": false, "report_reasons": null, "author": "sudophant", "can_mod_post": false, "send_replies": true, "parent_id": "t3_86a4c7", "score": 2, "approved_by": null, "downs": 0, "author_cakeday": true, "edited": false, "author_flair_css_class": null, "collapsed": false, "is_submitter": false, "collapsed_reason": null, "body_html": "&lt;div class=\"md\"&gt;&lt;p&gt;John Titor, you&amp;#39;ve changed maaan.&lt;/p&gt;\n&lt;/div&gt;", "subreddit_type": "public", "can_gild": true, "subreddit": "Bitcoin", "name": "t1_dw3lduz", "score_hidden": false, "permalink": "/r/Bitcoin/comments/86a4c7/countermessage_from_the_future/dw3lduz/", "num_reports": null, "stickied": false, "created": 1521748006.0, "author_flair_text": null, "created_utc": 1521719206.0, "subreddit_name_prefixed": "r/Bitcoin", "controversiality": 0, "depth": 0, "mod_reports": [], "mod_note": null, "distinguished": null}}, {"kind": "t1", "data": {"subreddit_id": "t5_2s3qj", "approved_at_utc": null, "ups": 2, "mod_reason_by": null, "banned_by": null, "removal_reason": null, "link_id": "t3_86a4c7", "likes": null, "no_follow": true, "replies": "", "user_reports": [], "saved": false, "id": "dw3hm3a", "banned_at_utc": null, "mod_reason_title": null, "gilded": 0, "archived": false, "report_reasons": null, "author": "Bitcoin-Yoda", "can_mod_post": false, "send_replies": true, "parent_id": "t3_86a4c7", "score": 2, "approved_by": null, "downs": 0, "body": "LOL good one :)", "edited": false, "author_flair_css_class": null, "collapsed": false, "is_submitter": false, "collapsed_reason": null, "body_html": "&lt;div class=\"md\"&gt;&lt;p&gt;LOL good one :)&lt;/p&gt;\n&lt;/div&gt;", "subreddit_type": "public", "can_gild": true, "subreddit": "Bitcoin", "name": "t1_dw3hm3a", "score_hidden": false, "permalink": "/r/Bitcoin/comments/86a4c7/countermessage_from_the_future/dw3hm3a/", "num_reports": null, "stickied": false, "created": 1521739910.0, "author_flair_text": null, "created_utc": 1521711110.0, "subreddit_name_prefixed": "r/Bitcoin", "controversiality": 0, "depth": 0, "mod_reports": [], "mod_note": null, "distinguished": null}}, {"kind": "t1", "data": {"subreddit_id": "t5_2s3qj", "approved_at_utc": null, "ups": 1, "mod_reason_by": null, "banned_by": null, "removal_reason": null, "link_id": "t3_86a4c7", "likes": null, "no_follow": true, "replies": {"kind": "Listing", "data": {"after": null, "whitelist_status": "all_ads", "modhash": "", "dist": null, "children": [{"kind": "t1", "data": {"subreddit_id": "t5_2s3qj", "approved_at_utc": null, "ups": 1, "mod_reason_by": null, "banned_by": null, "removal_reason": null, "link_id": "t3_86a4c7", "likes": null, "no_follow": true, "replies": "", "user_reports": [], "saved": false, "id": "dw43qlm", "banned_at_utc": null, "mod_reason_title": null, "gilded": 0, "archived": false, "report_reasons": null, "author": "ThisIsABeginning", "can_mod_post": false, "send_replies": true, "parent_id": "t1_dw3kwcz", "score": 1, "approved_by": null, "downs": 0, "body": "Hello Sir Rothschild. ", "edited": false, "author_flair_css_class": "noob", "collapsed": false, "is_submitter": true, "collapsed_reason": null, "body_html": "&lt;div class=\"md\"&gt;&lt;p&gt;Hello Sir Rothschild. &lt;/p&gt;\n&lt;/div&gt;", "subreddit_type": "public", "can_gild": true, "subreddit": "Bitcoin", "name": "t1_dw43qlm", "score_hidden": false, "permalink": "/r/Bitcoin/comments/86a4c7/countermessage_from_the_future/dw43qlm/", "num_reports": null, "stickied": false, "created": 1521767406.0, "author_flair_text": "redditor for 3 months", "created_utc": 1521738606.0, "subreddit_name_prefixed": "r/Bitcoin", "controversiality": 0, "depth": 1, "mod_reports": [], "mod_note": null, "distinguished": null}}], "before": null}}, "user_reports": [], "saved": false, "id": "dw3kwcz", "banned_at_utc": null, "mod_reason_title": null, "gilded": 0, "archived": false, "report_reasons": null, "author": "-Claymore-", "can_mod_post": false, "send_replies": true, "parent_id": "t3_86a4c7", "score": 1, "approved_by": null, "downs": 0, "body": "&gt; The wealth is no longer held in the hands of a few and the power to decide is hugely more democratic.\n\nLOL Now this is when we know it's bad imagination...", "edited": false, "author_flair_css_class": null, "collapsed": false, "is_submitter": false, "collapsed_reason": null, "body_html": "&lt;div class=\"md\"&gt;&lt;blockquote&gt;\n&lt;p&gt;The wealth is no longer held in the hands of a few and the power to decide is hugely more democratic.&lt;/p&gt;\n&lt;/blockquote&gt;\n\n&lt;p&gt;LOL Now this is when we know it&amp;#39;s bad imagination...&lt;/p&gt;\n&lt;/div&gt;", "subreddit_type": "public", "can_gild": true, "subreddit": "Bitcoin", "name": "t1_dw3kwcz", "score_hidden": false, "permalink": "/r/Bitcoin/comments/86a4c7/countermessage_from_the_future/dw3kwcz/", "num_reports": null, "stickied": false, "created": 1521747154.0, "author_flair_text": null, "created_utc": 1521718354.0, "subreddit_name_prefixed": "r/Bitcoin", "controversiality": 0, "depth": 0, "mod_reports": [], "mod_note": null, "distinguished": null}}, {"kind": "t1", "data": {"subreddit_id": "t5_2s3qj", "approved_at_utc": null, "ups": 1, "mod_reason_by": null, "banned_by": null, "removal_reason": null, "link_id": "t3_86a4c7", "likes": null, "no_follow": true, "replies": {"kind": "Listing", "data": {"after": null, "whitelist_status": "all_ads", "modhash": "", "dist": null, "children": [{"kind": "t1", "data": {"subreddit_id": "t5_2s3qj", "approved_at_utc": null, "ups": 2, "mod_reason_by": null, "banned_by": null, "removal_reason": null, "link_id": "t3_86a4c7", "likes": null, "no_follow": true, "replies": {"kind": "Listing", "data": {"after": null, "whitelist_status": "all_ads", "modhash": "", "dist": null, "children": [{"kind": "t1", "data": {"subreddit_id": "t5_2s3qj", "approved_at_utc": null, "ups": 1, "mod_reason_by": null, "banned_by": null, "removal_reason": null, "link_id": "t3_86a4c7", "likes": null, "no_follow": true, "replies": {"kind": "Listing", "data": {"after": null, "whitelist_status": "all_ads", "modhash": "", "dist": null, "children": [{"kind": "t1", "data": {"subreddit_id": "t5_2s3qj", "approved_at_utc": null, "ups": 1, "mod_reason_by": null, "banned_by": null, "removal_reason": null, "link_id": "t3_86a4c7", "likes": null, "no_follow": true, "replies": {"kind": "Listing", "data": {"after": null, "whitelist_status": "all_ads", "modhash": "", "dist": null, "children": [{"kind": "t1", "data": {"subreddit_id": "t5_2s3qj", "approved_at_utc": null, "ups": 1, "mod_reason_by": null, "banned_by": null, "removal_reason": null, "link_id": "t3_86a4c7", "likes": null, "no_follow": true, "replies": {"kind": "Listing", "data": {"after": null, "whitelist_status": "all_ads", "modhash": "", "dist": null, "children": [{"kind": "t1", "data": {"subreddit_id": "t5_2s3qj", "approved_at_utc": null, "ups": 1, "mod_reason_by": null, "banned_by": null, "removal_reason": null, "link_id": "t3_86a4c7", "likes": null, "no_follow": true, "replies": "", "user_reports": [], "saved": false, "id": "dw4etho", "banned_at_utc": null, "mod_reason_title": null, "gilded": 0, "archived": false, "report_reasons": null, "author": "ThisIsABeginning", "can_mod_post": false, "send_replies": true, "parent_id": "t1_dw4dudh", "score": 1, "approved_by": null, "downs": 0, "body": "(must....stay...in....character) Oh yes I understand the reference...Art imitates life... so the TV show you talk of was a real timeline that was cancelled because the Universe couldn\u2019t cope with the infinite loops...or was it Trevor? I forget. Anyway, now it\u2019s just a TV show. ", "edited": false, "author_flair_css_class": "noob", "collapsed": false, "is_submitter": true, "collapsed_reason": null, "body_html": "&lt;div class=\"md\"&gt;&lt;p&gt;(must....stay...in....character) Oh yes I understand the reference...Art imitates life... so the TV show you talk of was a real timeline that was cancelled because the Universe couldn\u2019t cope with the infinite loops...or was it Trevor? I forget. Anyway, now it\u2019s just a TV show. &lt;/p&gt;\n&lt;/div&gt;", "subreddit_type": "public", "can_gild": true, "subreddit": "Bitcoin", "name": "t1_dw4etho", "score_hidden": false, "permalink": "/r/Bitcoin/comments/86a4c7/countermessage_from_the_future/dw4etho/", "num_reports": null, "stickied": false, "created": 1521777367.0, "author_flair_text": "redditor for 3 months", "created_utc": 1521748567.0, "subreddit_name_prefixed": "r/Bitcoin", "controversiality": 0, "depth": 5, "mod_reports": [], "mod_note": null, "distinguished": null}}], "before": null}}, "user_reports": [], "saved": false, "id": "dw4dudh", "banned_at_utc": null, "mod_reason_title": null, "gilded": 0, "archived": false, "report_reasons": null, "author": "slcannon97", "can_mod_post": false, "send_replies": true, "parent_id": "t1_dw4dqnb", "score": 1, "approved_by": null, "downs": 0, "body": "You should look up travelers on Netflix. Great show, if you watch it you'll get my reference ", "edited": false, "author_flair_css_class": null, "collapsed": false, "is_submitter": false, "collapsed_reason": null, "body_html": "&lt;div class=\"md\"&gt;&lt;p&gt;You should look up travelers on Netflix. Great show, if you watch it you&amp;#39;ll get my reference &lt;/p&gt;\n&lt;/div&gt;", "subreddit_type": "public", "can_gild": true, "subreddit": "Bitcoin", "name": "t1_dw4dudh", "score_hidden": false, "permalink": "/r/Bitcoin/comments/86a4c7/countermessage_from_the_future/dw4dudh/", "num_reports": null, "stickied": false, "created": 1521776488.0, "author_flair_text": null, "created_utc": 1521747688.0, "subreddit_name_prefixed": "r/Bitcoin", "controversiality": 0, "depth": 4, "mod_reports": [], "mod_note": null, "distinguished": null}}], "before": null}}, "user_reports": [], "saved": false, "id": "dw4dqnb", "banned_at_utc": null, "mod_reason_title": null, "gilded": 0, "archived": false, "report_reasons": null, "author": "ThisIsABeginning", "can_mod_post": false, "send_replies": true, "parent_id": "t1_dw47bwk", "score": 1, "approved_by": null, "downs": 0, "body": "I am from the Core. Directors no longer exist in business or society as consensus rules the day. The timeline and its branches you are talking of no longer exist. It was duly cancelled for being too confusing. ", "edited": false, "author_flair_css_class": "noob", "collapsed": false, "is_submitter": true, "collapsed_reason": null, "body_html": "&lt;div class=\"md\"&gt;&lt;p&gt;I am from the Core. Directors no longer exist in business or society as consensus rules the day. The timeline and its branches you are talking of no longer exist. It was duly cancelled for being too confusing. &lt;/p&gt;\n&lt;/div&gt;", "subreddit_type": "public", "can_gild": true, "subreddit": "Bitcoin", "name": "t1_dw4dqnb", "score_hidden": false, "permalink": "/r/Bitcoin/comments/86a4c7/countermessage_from_the_future/dw4dqnb/", "num_reports": null, "stickied": false, "created": 1521776393.0, "author_flair_text": "redditor for 3 months", "created_utc": 1521747593.0, "subreddit_name_prefixed": "r/Bitcoin", "controversiality": 0, "depth": 3, "mod_reports": [], "mod_note": null, "distinguished": null}}], "before": null}}, "user_reports": [], "saved": false, "id": "dw47bwk", "banned_at_utc": null, "mod_reason_title": null, "gilded": 0, "archived": false, "report_reasons": null, "author": "slcannon97", "can_mod_post": false, "send_replies": true, "parent_id": "t1_dw43n3f", "score": 1, "approved_by": null, "downs": 0, "body": "Had to check. Did the director send you or are you faction? What's your traveler #?", "edited": false, "author_flair_css_class": null, "collapsed": false, "is_submitter": false, "collapsed_reason": null, "body_html": "&lt;div class=\"md\"&gt;&lt;p&gt;Had to check. Did the director send you or are you faction? What&amp;#39;s your traveler #?&lt;/p&gt;\n&lt;/div&gt;", "subreddit_type": "public", "can_gild": true, "subreddit": "Bitcoin", "name": "t1_dw47bwk", "score_hidden": false, "permalink": "/r/Bitcoin/comments/86a4c7/countermessage_from_the_future/dw47bwk/", "num_reports": null, "stickied": false, "created": 1521770585.0, "author_flair_text": null, "created_utc": 1521741785.0, "subreddit_name_prefixed": "r/Bitcoin", "controversiality": 0, "depth": 2, "mod_reports": [], "mod_note": null, "distinguished": null}}], "before": null}}, "user_reports": [], "saved": false, "id": "dw43n3f", "banned_at_utc": null, "mod_reason_title": null, "gilded": 0, "archived": false, "report_reasons": null, "author": "ThisIsABeginning", "can_mod_post": false, "send_replies": true, "parent_id": "t1_dw3wjpy", "score": 2, "approved_by": null, "downs": 0, "body": "Time travel is done by assuming the consciousness of a local body...I arrived today. didn\u2019t you know that already? \ud83d\ude01 btw BCH died long ago in my timeline as well as the other trash coins. ", "edited": false, "author_flair_css_class": "noob", "collapsed": false, "is_submitter": true, "collapsed_reason": null, "body_html": "&lt;div class=\"md\"&gt;&lt;p&gt;Time travel is done by assuming the consciousness of a local body...I arrived today. didn\u2019t you know that already? \ud83d\ude01 btw BCH died long ago in my timeline as well as the other trash coins. &lt;/p&gt;\n&lt;/div&gt;", "subreddit_type": "public", "can_gild": true, "subreddit": "Bitcoin", "name": "t1_dw43n3f", "score_hidden": false, "permalink": "/r/Bitcoin/comments/86a4c7/countermessage_from_the_future/dw43n3f/", "num_reports": null, "stickied": false, "created": 1521767318.0, "author_flair_text": "redditor for 3 months", "created_utc": 1521738518.0, "subreddit_name_prefixed": "r/Bitcoin", "controversiality": 0, "depth": 1, "mod_reports": [], "mod_note": null, "distinguished": null}}], "before": null}}, "user_reports": [], "saved": false, "id": "dw3wjpy", "banned_at_utc": null, "mod_reason_title": null, "gilded": 0, "archived": false, "report_reasons": null, "author": "slcannon97", "can_mod_post": false, "send_replies": true, "parent_id": "t3_86a4c7", "score": 1, "approved_by": null, "downs": 0, "body": "How can you claim to be from the future but made a post 68 days ago about whether selling BCH was a good idea? Wouldn't you already know", "edited": false, "author_flair_css_class": null, "collapsed": false, "is_submitter": false, "collapsed_reason": null, "body_html": "&lt;div class=\"md\"&gt;&lt;p&gt;How can you claim to be from the future but made a post 68 days ago about whether selling BCH was a good idea? Wouldn&amp;#39;t you already know&lt;/p&gt;\n&lt;/div&gt;", "subreddit_type": "public", "can_gild": true, "subreddit": "Bitcoin", "name": "t1_dw3wjpy", "score_hidden": false, "permalink": "/r/Bitcoin/comments/86a4c7/countermessage_from_the_future/dw3wjpy/", "num_reports": null, "stickied": false, "created": 1521760951.0, "author_flair_text": null, "created_utc": 1521732151.0, "subreddit_name_prefixed": "r/Bitcoin", "controversiality": 0, "depth": 0, "mod_reports": [], "mod_note": null, "distinguished": null}}, {"kind": "t1", "data": {"subreddit_id": "t5_2s3qj", "approved_at_utc": null, "ups": 1, "mod_reason_by": null, "banned_by": null, "removal_reason": null, "link_id": "t3_86a4c7", "likes": null, "no_follow": true, "replies": "", "user_reports": [], "saved": false, "id": "dw5a13a", "banned_at_utc": null, "mod_reason_title": null, "gilded": 0, "archived": false, "report_reasons": null, "author": "ghee99", "can_mod_post": false, "send_replies": true, "parent_id": "t3_86a4c7", "score": 1, "approved_by": null, "downs": 0, "body": "hey future man,\n\njust curious, but how long did it take before the people realized what a crook ex-president obama was, and had him sent off to jail?", "edited": false, "author_flair_css_class": null, "collapsed": false, "is_submitter": false, "collapsed_reason": null, "body_html": "&lt;div class=\"md\"&gt;&lt;p&gt;hey future man,&lt;/p&gt;\n\n&lt;p&gt;just curious, but how long did it take before the people realized what a crook ex-president obama was, and had him sent off to jail?&lt;/p&gt;\n&lt;/div&gt;", "subreddit_type": "public", "can_gild": true, "subreddit": "Bitcoin", "name": "t1_dw5a13a", "score_hidden": false, "permalink": "/r/Bitcoin/comments/86a4c7/countermessage_from_the_future/dw5a13a/", "num_reports": null, "stickied": false, "created": 1521810042.0, "author_flair_text": null, "created_utc": 1521781242.0, "subreddit_name_prefixed": "r/Bitcoin", "controversiality": 0, "depth": 0, "mod_reports": [], "mod_note": null, "distinguished": null}}], "before": null}