{"after": null, "whitelist_status": "all_ads", "modhash": "", "dist": null, "children": [{"kind": "t1", "data": {"subreddit_id": "t5_2s3qj", "approved_at_utc": null, "ups": 2, "mod_reason_by": null, "banned_by": null, "removal_reason": null, "link_id": "t3_87m3ta", "likes": null, "no_follow": true, "replies": "", "user_reports": [], "saved": false, "id": "dwejgrs", "banned_at_utc": null, "mod_reason_title": null, "gilded": 0, "archived": false, "report_reasons": null, "author": "ZepCoin", "can_mod_post": false, "send_replies": true, "parent_id": "t3_87m3ta", "score": 2, "approved_by": null, "downs": 0, "body": "All mining nodes are continuously trying to add a block of transactions to the chain of blocks with the greatest Proof Of Work. If the network is cut in half, then two chains will be maintained until the network mends. At that time the chain with the least amount of POW will be abandoned by all of the nodes that become aware of the higher POW chain. No miners want to spend $ on electricity to add to a chain that is about to be abandoned, and all miners are highly motivated to take the most likely path towards claiming a block reward on the chain that they estimate to be most likely to win.", "edited": false, "author_flair_css_class": "noob", "collapsed": false, "is_submitter": false, "collapsed_reason": null, "body_html": "&lt;div class=\"md\"&gt;&lt;p&gt;All mining nodes are continuously trying to add a block of transactions to the chain of blocks with the greatest Proof Of Work. If the network is cut in half, then two chains will be maintained until the network mends. At that time the chain with the least amount of POW will be abandoned by all of the nodes that become aware of the higher POW chain. No miners want to spend $ on electricity to add to a chain that is about to be abandoned, and all miners are highly motivated to take the most likely path towards claiming a block reward on the chain that they estimate to be most likely to win.&lt;/p&gt;\n&lt;/div&gt;", "subreddit_type": "public", "can_gild": true, "subreddit": "Bitcoin", "name": "t1_dwejgrs", "score_hidden": false, "permalink": "/r/Bitcoin/comments/87m3ta/in_a_network_segmentation_how_does_bitcoins_proof/dwejgrs/", "num_reports": null, "stickied": false, "created": 1522239938.0, "author_flair_text": "redditor for 3 months", "created_utc": 1522211138.0, "subreddit_name_prefixed": "r/Bitcoin", "controversiality": 0, "depth": 0, "mod_reports": [], "mod_note": null, "distinguished": null}}, {"kind": "t1", "data": {"subreddit_id": "t5_2s3qj", "approved_at_utc": null, "ups": 1, "mod_reason_by": null, "banned_by": null, "removal_reason": null, "link_id": "t3_87m3ta", "likes": null, "no_follow": true, "replies": {"kind": "Listing", "data": {"after": null, "whitelist_status": "all_ads", "modhash": "", "dist": null, "children": [{"kind": "t1", "data": {"subreddit_id": "t5_2s3qj", "approved_at_utc": null, "ups": 1, "mod_reason_by": null, "banned_by": null, "removal_reason": null, "link_id": "t3_87m3ta", "likes": null, "no_follow": true, "replies": {"kind": "Listing", "data": {"after": null, "whitelist_status": "all_ads", "modhash": "", "dist": null, "children": [{"kind": "t1", "data": {"subreddit_id": "t5_2s3qj", "approved_at_utc": null, "ups": 2, "mod_reason_by": null, "banned_by": null, "removal_reason": null, "link_id": "t3_87m3ta", "likes": null, "no_follow": true, "replies": {"kind": "Listing", "data": {"after": null, "whitelist_status": "all_ads", "modhash": "", "dist": null, "children": [{"kind": "t1", "data": {"subreddit_id": "t5_2s3qj", "approved_at_utc": null, "ups": 1, "mod_reason_by": null, "banned_by": null, "removal_reason": null, "link_id": "t3_87m3ta", "likes": null, "no_follow": true, "replies": {"kind": "Listing", "data": {"after": null, "whitelist_status": "all_ads", "modhash": "", "dist": null, "children": [{"kind": "t1", "data": {"subreddit_id": "t5_2s3qj", "approved_at_utc": null, "ups": 6, "mod_reason_by": null, "banned_by": null, "removal_reason": null, "link_id": "t3_87m3ta", "likes": null, "no_follow": true, "replies": {"kind": "Listing", "data": {"after": null, "whitelist_status": "all_ads", "modhash": "", "dist": null, "children": [{"kind": "t1", "data": {"subreddit_id": "t5_2s3qj", "approved_at_utc": null, "ups": 2, "mod_reason_by": null, "banned_by": null, "removal_reason": null, "link_id": "t3_87m3ta", "likes": null, "no_follow": true, "replies": "", "user_reports": [], "saved": false, "id": "dwdzwua", "banned_at_utc": null, "mod_reason_title": null, "gilded": 0, "archived": false, "report_reasons": null, "author": "MixedTrailMix", "can_mod_post": false, "send_replies": true, "parent_id": "t1_dwdvmn7", "score": 2, "approved_by": null, "downs": 0, "body": "thank you!!! ", "edited": false, "author_flair_css_class": null, "collapsed": false, "is_submitter": true, "collapsed_reason": null, "body_html": "&lt;div class=\"md\"&gt;&lt;p&gt;thank you!!! &lt;/p&gt;\n&lt;/div&gt;", "subreddit_type": "public", "can_gild": true, "subreddit": "Bitcoin", "name": "t1_dwdzwua", "score_hidden": false, "permalink": "/r/Bitcoin/comments/87m3ta/in_a_network_segmentation_how_does_bitcoins_proof/dwdzwua/", "num_reports": null, "stickied": false, "created": 1522218597.0, "author_flair_text": null, "created_utc": 1522189797.0, "subreddit_name_prefixed": "r/Bitcoin", "controversiality": 0, "depth": 5, "mod_reports": [], "mod_note": null, "distinguished": null}}], "before": null}}, "user_reports": [], "saved": false, "id": "dwdvmn7", "banned_at_utc": null, "mod_reason_title": null, "gilded": 0, "archived": false, "report_reasons": null, "author": "tripledogdareya", "can_mod_post": false, "send_replies": true, "parent_id": "t1_dwdur4l", "score": 6, "approved_by": null, "downs": 0, "body": "The PoW is a block header, linked to the previous block header by inclusion of its hash, that when itself hashed satisfies the difficulty requirements of the chain. Once a miner has done the work of finding such a block header, it is broadcast to the network.\n\nConsensus comes not from any one node or block, but from the accumulation of work proof, demonstrated by the network's approval of a chain of such headers and signaled by the majority of hash power being expended in its creation. The need to accumulate work proof is behind the requirement for multiple confirmations. Observing consensus is a probabilistic exercise. Only once you have seen sufficient demonstration of accumlated work proof can you be confident that it must be the product of the majority of work output and, consequently, no other source of work could out proof it.", "edited": 1522186742.0, "author_flair_css_class": null, "collapsed": false, "is_submitter": false, "collapsed_reason": null, "body_html": "&lt;div class=\"md\"&gt;&lt;p&gt;The PoW is a block header, linked to the previous block header by inclusion of its hash, that when itself hashed satisfies the difficulty requirements of the chain. Once a miner has done the work of finding such a block header, it is broadcast to the network.&lt;/p&gt;\n\n&lt;p&gt;Consensus comes not from any one node or block, but from the accumulation of work proof, demonstrated by the network&amp;#39;s approval of a chain of such headers and signaled by the majority of hash power being expended in its creation. The need to accumulate work proof is behind the requirement for multiple confirmations. Observing consensus is a probabilistic exercise. Only once you have seen sufficient demonstration of accumlated work proof can you be confident that it must be the product of the majority of work output and, consequently, no other source of work could out proof it.&lt;/p&gt;\n&lt;/div&gt;", "subreddit_type": "public", "can_gild": true, "subreddit": "Bitcoin", "name": "t1_dwdvmn7", "score_hidden": false, "permalink": "/r/Bitcoin/comments/87m3ta/in_a_network_segmentation_how_does_bitcoins_proof/dwdvmn7/", "num_reports": null, "stickied": false, "created": 1522214389.0, "author_flair_text": null, "created_utc": 1522185589.0, "subreddit_name_prefixed": "r/Bitcoin", "controversiality": 0, "depth": 4, "mod_reports": [], "mod_note": null, "distinguished": null}}], "before": null}}, "user_reports": [], "saved": false, "id": "dwdur4l", "banned_at_utc": null, "mod_reason_title": null, "gilded": 0, "archived": false, "report_reasons": null, "author": "MixedTrailMix", "can_mod_post": false, "send_replies": true, "parent_id": "t1_dwdujm9", "score": 1, "approved_by": null, "downs": 0, "body": "Oops. Not how its physically transported over the network.......youre saying as soon as its done with  PoW it gets pushed to every node. And that the verification of that node is the consensus?", "edited": false, "author_flair_css_class": null, "collapsed": false, "is_submitter": true, "collapsed_reason": null, "body_html": "&lt;div class=\"md\"&gt;&lt;p&gt;Oops. Not how its physically transported over the network.......youre saying as soon as its done with  PoW it gets pushed to every node. And that the verification of that node is the consensus?&lt;/p&gt;\n&lt;/div&gt;", "subreddit_type": "public", "can_gild": true, "subreddit": "Bitcoin", "name": "t1_dwdur4l", "score_hidden": false, "permalink": "/r/Bitcoin/comments/87m3ta/in_a_network_segmentation_how_does_bitcoins_proof/dwdur4l/", "num_reports": null, "stickied": false, "created": 1522213577.0, "author_flair_text": null, "created_utc": 1522184777.0, "subreddit_name_prefixed": "r/Bitcoin", "controversiality": 0, "depth": 3, "mod_reports": [], "mod_note": null, "distinguished": null}}], "before": null}}, "user_reports": [], "saved": false, "id": "dwdujm9", "banned_at_utc": null, "mod_reason_title": null, "gilded": 0, "archived": false, "report_reasons": null, "author": "[deleted]", "can_mod_post": false, "send_replies": true, "parent_id": "t1_dwduhku", "score": 2, "approved_by": null, "downs": 0, "body": "[deleted]", "edited": false, "author_flair_css_class": null, "collapsed": false, "is_submitter": false, "collapsed_reason": null, "body_html": "&lt;div class=\"md\"&gt;&lt;p&gt;[deleted]&lt;/p&gt;\n&lt;/div&gt;", "subreddit_type": "public", "can_gild": true, "subreddit": "Bitcoin", "name": "t1_dwdujm9", "score_hidden": false, "permalink": "/r/Bitcoin/comments/87m3ta/in_a_network_segmentation_how_does_bitcoins_proof/dwdujm9/", "num_reports": null, "stickied": false, "created": 1522213389.0, "author_flair_text": null, "created_utc": 1522184589.0, "subreddit_name_prefixed": "r/Bitcoin", "controversiality": 0, "depth": 2, "mod_reports": [], "mod_note": null, "distinguished": null}}], "before": null}}, "user_reports": [], "saved": false, "id": "dwduhku", "banned_at_utc": null, "mod_reason_title": null, "gilded": 0, "archived": false, "report_reasons": null, "author": "MixedTrailMix", "can_mod_post": false, "send_replies": true, "parent_id": "t1_dwdudun", "score": 1, "approved_by": null, "downs": 0, "body": "But how do they distribute the blocks", "edited": false, "author_flair_css_class": null, "collapsed": false, "is_submitter": true, "collapsed_reason": null, "body_html": "&lt;div class=\"md\"&gt;&lt;p&gt;But how do they distribute the blocks&lt;/p&gt;\n&lt;/div&gt;", "subreddit_type": "public", "can_gild": true, "subreddit": "Bitcoin", "name": "t1_dwduhku", "score_hidden": false, "permalink": "/r/Bitcoin/comments/87m3ta/in_a_network_segmentation_how_does_bitcoins_proof/dwduhku/", "num_reports": null, "stickied": false, "created": 1522213336.0, "author_flair_text": null, "created_utc": 1522184536.0, "subreddit_name_prefixed": "r/Bitcoin", "controversiality": 0, "depth": 1, "mod_reports": [], "mod_note": null, "distinguished": null}}], "before": null}}, "user_reports": [], "saved": false, "id": "dwdudun", "banned_at_utc": null, "mod_reason_title": null, "gilded": 0, "archived": false, "report_reasons": null, "author": "[deleted]", "can_mod_post": false, "send_replies": true, "parent_id": "t3_87m3ta", "score": 1, "approved_by": null, "downs": 0, "body": "[deleted]", "edited": false, "author_flair_css_class": null, "collapsed": false, "is_submitter": false, "collapsed_reason": null, "body_html": "&lt;div class=\"md\"&gt;&lt;p&gt;[deleted]&lt;/p&gt;\n&lt;/div&gt;", "subreddit_type": "public", "can_gild": true, "subreddit": "Bitcoin", "name": "t1_dwdudun", "score_hidden": false, "permalink": "/r/Bitcoin/comments/87m3ta/in_a_network_segmentation_how_does_bitcoins_proof/dwdudun/", "num_reports": null, "stickied": false, "created": 1522213240.0, "author_flair_text": null, "created_utc": 1522184440.0, "subreddit_name_prefixed": "r/Bitcoin", "controversiality": 0, "depth": 0, "mod_reports": [], "mod_note": null, "distinguished": null}}, {"kind": "t1", "data": {"subreddit_id": "t5_2s3qj", "approved_at_utc": null, "ups": 0, "mod_reason_by": null, "banned_by": null, "removal_reason": null, "link_id": "t3_87m3ta", "likes": null, "no_follow": true, "replies": "", "user_reports": [], "saved": false, "id": "dweonr4", "banned_at_utc": null, "mod_reason_title": null, "gilded": 0, "archived": false, "report_reasons": null, "author": "ep7i0CtZek", "can_mod_post": false, "send_replies": true, "parent_id": "t3_87m3ta", "score": 0, "approved_by": null, "downs": 0, "body": "It might eventually cause a network split. Two coins. ", "edited": false, "author_flair_css_class": null, "collapsed": false, "is_submitter": false, "collapsed_reason": null, "body_html": "&lt;div class=\"md\"&gt;&lt;p&gt;It might eventually cause a network split. Two coins. &lt;/p&gt;\n&lt;/div&gt;", "subreddit_type": "public", "can_gild": true, "subreddit": "Bitcoin", "name": "t1_dweonr4", "score_hidden": false, "permalink": "/r/Bitcoin/comments/87m3ta/in_a_network_segmentation_how_does_bitcoins_proof/dweonr4/", "num_reports": null, "stickied": false, "created": 1522248848.0, "author_flair_text": null, "created_utc": 1522220048.0, "subreddit_name_prefixed": "r/Bitcoin", "controversiality": 0, "depth": 0, "mod_reports": [], "mod_note": null, "distinguished": null}}], "before": null}