{"after": "t3_84zhqb", "dist": 27, "modhash": "", "whitelist_status": "all_ads", "children": [{"kind": "t3", "data": {"subreddit_id": "t5_2s3qj", "approved_at_utc": null, "send_replies": true, "mod_reason_by": null, "banned_by": null, "num_reports": null, "removal_reason": null, "thumbnail_width": null, "subreddit": "Bitcoin", "selftext_html": null, "selftext": "", "likes": null, "suggested_sort": null, "user_reports": [], "secure_media": null, "is_reddit_media_domain": false, "saved": false, "id": "84n7dl", "banned_at_utc": null, "mod_reason_title": null, "view_count": null, "archived": false, "clicked": false, "no_follow": false, "author": "roasbeef", "num_crossposts": 1, "link_flair_text": null, "mod_reports": [], "can_mod_post": false, "is_crosspostable": false, "pinned": false, "score": 1834, "approved_by": null, "over_18": false, "report_reasons": null, "domain": "blog.lightning.engineering", "hidden": false, "thumbnail": "default", "edited": false, "link_flair_css_class": null, "author_flair_css_class": "lightningexpert", "contest_mode": false, "gilded": 1, "downs": 0, "brand_safe": true, "secure_media_embed": {}, "media_embed": {}, "author_flair_text": "Lightning Network Expert", "stickied": true, "visited": false, "can_gild": false, "thumbnail_height": null, "parent_whitelist_status": "all_ads", "name": "t3_84n7dl", "spoiler": false, "permalink": "/r/Bitcoin/comments/84n7dl/announcing_lnd_04beta/", "subreddit_type": "public", "locked": false, "hide_score": false, "created": 1521155675.0, "url": "https://blog.lightning.engineering/announcement/2018/03/15/lnd-beta.html#", "whitelist_status": "all_ads", "quarantine": false, "subreddit_subscribers": 772141, "created_utc": 1521126875.0, "subreddit_name_prefixed": "r/Bitcoin", "ups": 1834, "media": null, "num_comments": 293, "is_self": false, "title": "\u26a1\ufe0fAnnouncing LND 0.4-beta \u26a1\ufe0f", "mod_note": null, "is_video": false, "distinguished": null}}, {"kind": "t3", "data": {"subreddit_id": "t5_2s3qj", "approved_at_utc": null, "send_replies": false, "mod_reason_by": null, "banned_by": null, "num_reports": null, "removal_reason": null, "thumbnail_width": null, "subreddit": "Bitcoin", "selftext_html": "&lt;!-- SC_OFF --&gt;&lt;div class=\"md\"&gt;&lt;p&gt;Please utilize this sticky thread for all general &lt;strong&gt;Bitcoin&lt;/strong&gt; discussions! If you see posts on the front page or &lt;a href=\"/r/Bitcoin/new\"&gt;/r/Bitcoin/new&lt;/a&gt; which are better suited for this daily discussion thread, please help out by directing the OP to this thread instead. Thank you!&lt;/p&gt;\n\n&lt;p&gt;Daily threads are fast paced! If you don&amp;#39;t get an answer to your question, you can try phrasing it differently or commenting again tomorrow.&lt;/p&gt;\n\n&lt;h2&gt;Suggested Topics&lt;/h2&gt;\n\n&lt;ul&gt;\n&lt;li&gt;Screenshots\n\n&lt;ul&gt;\n&lt;li&gt;of article headlines without the article&lt;/li&gt;\n&lt;li&gt;of your favorite price ticker&lt;/li&gt;\n&lt;li&gt;of your exchange website&lt;/li&gt;\n&lt;li&gt;of your private chats&lt;/li&gt;\n&lt;/ul&gt;&lt;/li&gt;\n&lt;li&gt;Wallet/Exchange/Network\n\n&lt;ul&gt;\n&lt;li&gt;recommendations&lt;/li&gt;\n&lt;li&gt;complaints&lt;/li&gt;\n&lt;li&gt;service outages&lt;/li&gt;\n&lt;li&gt;troubleshooting&lt;/li&gt;\n&lt;li&gt;fee estimation&lt;/li&gt;\n&lt;li&gt;unconfirmed transactions&lt;/li&gt;\n&lt;/ul&gt;&lt;/li&gt;\n&lt;li&gt;All things price\n\n&lt;ul&gt;\n&lt;li&gt;hodling&lt;/li&gt;\n&lt;li&gt;the dip&lt;/li&gt;\n&lt;li&gt;the moon&lt;/li&gt;\n&lt;li&gt;price going up&lt;/li&gt;\n&lt;li&gt;price going down&lt;/li&gt;\n&lt;li&gt;technical analysis&lt;/li&gt;\n&lt;li&gt;price on your smart phone&lt;/li&gt;\n&lt;li&gt;price on your smart watch&lt;/li&gt;\n&lt;/ul&gt;&lt;/li&gt;\n&lt;li&gt;Stuff you bought with Bitcoin\n\n&lt;ul&gt;\n&lt;li&gt;Hardware wallets&lt;/li&gt;\n&lt;li&gt;Lambos&lt;/li&gt;\n&lt;li&gt;Teslas&lt;/li&gt;\n&lt;li&gt;Pizza&lt;/li&gt;\n&lt;/ul&gt;&lt;/li&gt;\n&lt;li&gt;Questions\n\n&lt;ul&gt;\n&lt;li&gt;Receiving Bitcoin&lt;/li&gt;\n&lt;li&gt;Sending Bitcoin&lt;/li&gt;\n&lt;li&gt;Earning Bitcoin&lt;/li&gt;\n&lt;li&gt;Storing Bitcoin&lt;/li&gt;\n&lt;li&gt;Buying Bitcoin&lt;/li&gt;\n&lt;li&gt;Selling Bitcoin&lt;/li&gt;\n&lt;/ul&gt;&lt;/li&gt;\n&lt;li&gt;That thing your coworker said&lt;/li&gt;\n&lt;li&gt;Bitcoin Showerthoughts&lt;/li&gt;\n&lt;li&gt;Random music videos&lt;/li&gt;\n&lt;li&gt;Bitcoin license plates&lt;/li&gt;\n&lt;li&gt;Interesting threads&lt;/li&gt;\n&lt;li&gt;Future speculation&lt;/li&gt;\n&lt;li&gt;News of the day&lt;/li&gt;\n&lt;li&gt;Memes, GIFs&lt;/li&gt;\n&lt;li&gt;Twitter links&lt;/li&gt;\n&lt;/ul&gt;\n\n&lt;p&gt;&lt;strong&gt;Your price screenshots and repetitive submissions are being removed, so please stop submitting them!&lt;/strong&gt;&lt;/p&gt;\n\n&lt;p&gt;Please check the &lt;a href=\"https://www.reddit.com/r/Bitcoin/comments/84uapw/daily_discussion_march_16_2018/\"&gt;previous discussion thread&lt;/a&gt; for unanswered questions.&lt;/p&gt;\n&lt;/div&gt;&lt;!-- SC_ON --&gt;", "selftext": "Please utilize this sticky thread for all general **Bitcoin** discussions! If you see posts on the front page or /r/Bitcoin/new which are better suited for this daily discussion thread, please help out by directing the OP to this thread instead. Thank you!\r\n\r\nDaily threads are fast paced! If you don't get an answer to your question, you can try phrasing it differently or commenting again tomorrow.\r\n\r\n## Suggested Topics\r\n\r\n* Screenshots\r\n  * of article headlines without the article\r\n  * of your favorite price ticker\r\n  * of your exchange website\r\n  * of your private chats\r\n* Wallet/Exchange/Network\r\n  * recommendations\r\n  * complaints\r\n  * service outages\r\n  * troubleshooting\r\n  * fee estimation\r\n  * unconfirmed transactions\r\n* All things price\r\n  * hodling\r\n  * the dip\r\n  * the moon\r\n  * price going up\r\n  * price going down\r\n  * technical analysis\r\n  * price on your smart phone\r\n  * price on your smart watch\r\n* Stuff you bought with Bitcoin\r\n  * Hardware wallets\r\n  * Lambos\r\n  * Teslas\r\n  * Pizza\r\n* Questions\r\n  * Receiving Bitcoin\r\n  * Sending Bitcoin\r\n  * Earning Bitcoin\r\n  * Storing Bitcoin\r\n  * Buying Bitcoin\r\n  * Selling Bitcoin\r\n* That thing your coworker said\r\n* Bitcoin Showerthoughts\r\n* Random music videos\r\n* Bitcoin license plates\r\n* Interesting threads\r\n* Future speculation\r\n* News of the day\r\n* Memes, GIFs\r\n* Twitter links\r\n\r\n**Your price screenshots and repetitive submissions are being removed, so please stop submitting them!**\n\nPlease check the [previous discussion thread](https://www.reddit.com/r/Bitcoin/comments/84uapw/daily_discussion_march_16_2018/) for unanswered questions.", "likes": null, "suggested_sort": "new", "user_reports": [], "secure_media": null, "is_reddit_media_domain": false, "saved": false, "id": "852ug0", "banned_at_utc": null, "mod_reason_title": null, "view_count": null, "archived": false, "clicked": false, "no_follow": false, "author": "rBitcoinMod", "num_crossposts": 0, "link_flair_text": null, "mod_reports": [], "can_mod_post": false, "is_crosspostable": false, "pinned": false, "score": 16, "approved_by": null, "over_18": false, "report_reasons": null, "domain": "self.Bitcoin", "hidden": false, "thumbnail": "self", "edited": false, "link_flair_css_class": null, "author_flair_css_class": null, "contest_mode": false, "gilded": 0, "downs": 0, "brand_safe": true, "secure_media_embed": {}, "media_embed": {}, "author_flair_text": null, "stickied": true, "visited": false, "can_gild": false, "thumbnail_height": null, "parent_whitelist_status": "all_ads", "name": "t3_852ug0", "spoiler": false, "permalink": "/r/Bitcoin/comments/852ug0/daily_discussion_march_17_2018/", "subreddit_type": "public", "locked": false, "hide_score": false, "created": 1521309606.0, "url": "https://www.reddit.com/r/Bitcoin/comments/852ug0/daily_discussion_march_17_2018/", "whitelist_status": "all_ads", "quarantine": false, "subreddit_subscribers": 772141, "created_utc": 1521280806.0, "subreddit_name_prefixed": "r/Bitcoin", "ups": 16, "media": null, "num_comments": 151, "is_self": true, "title": "Daily Discussion, March 17, 2018", "mod_note": null, "is_video": false, "distinguished": "moderator"}}, {"kind": "t3", "data": {"subreddit_id": "t5_2s3qj", "approved_at_utc": null, "send_replies": true, "mod_reason_by": null, "banned_by": null, "num_reports": null, "removal_reason": null, "thumbnail_width": 140, "subreddit": "Bitcoin", "selftext_html": null, "selftext": "", "likes": null, "suggested_sort": null, "user_reports": [], "secure_media": {"oembed": {"provider_url": "https://www.streamable.com", "description": "Check out this video on Streamable using your phone, tablet or desktop.", "title": "bitcoin_stitch - Streamable", "type": "video", "thumbnail_width": 1280, "height": 338, "width": 600, "html": "&lt;iframe class=\"embedly-embed\" src=\"https://cdn.embedly.com/widgets/media.html?src=https%3A%2F%2Fstreamable.com%2Ft%2Fd22zx&amp;url=https%3A%2F%2Fstreamable.com%2Fd22zx&amp;image=https%3A%2F%2Fcf-e2.streamablevideo.com%2Fimage%2Fd22zx.jpg%3Ftoken%3D1521291289-I%252FrB3x9jEgiLjaew%252BxfrrcQlPbLGZoAInry%252FbdpE%252BaM%253D&amp;key=2aa3c4d5f3de4f5b9120b660ad850dc9&amp;type=text%2Fhtml&amp;schema=streamable\" width=\"600\" height=\"338\" scrolling=\"no\" frameborder=\"0\" allowfullscreen&gt;&lt;/iframe&gt;", "version": "1.0", "provider_name": "Streamable", "thumbnail_url": "https://i.embed.ly/1/image?url=https%3A%2F%2Fcf-e2.streamablevideo.com%2Fimage%2Fd22zx.jpg%3Ftoken%3D1521291289-I%252FrB3x9jEgiLjaew%252BxfrrcQlPbLGZoAInry%252FbdpE%252BaM%253D&amp;key=b1e305db91cf4aa5a86b732cc9fffceb", "thumbnail_height": 720}, "type": "streamable.com"}, "is_reddit_media_domain": false, "saved": false, "id": "853jyn", "banned_at_utc": null, "mod_reason_title": null, "view_count": null, "archived": false, "clicked": false, "no_follow": false, "author": "BananenMatsch", "num_crossposts": 1, "link_flair_text": null, "mod_reports": [], "can_mod_post": false, "is_crosspostable": false, "pinned": false, "score": 501, "approved_by": null, "over_18": false, "report_reasons": null, "domain": "streamable.com", "hidden": false, "preview": {"images": [{"source": {"url": "https://i.redditmedia.com/HIYBBOwflneGk8bg8_j4iRQ8Xp_wGH3p0U9TxN5SDQE.jpg?fm=jpg&amp;s=93cd2cef4f8af0a85b50a76a98e506b2", "width": 1280, "height": 720}, "resolutions": [{"url": "https://i.redditmedia.com/HIYBBOwflneGk8bg8_j4iRQ8Xp_wGH3p0U9TxN5SDQE.jpg?fit=crop&amp;crop=faces%2Centropy&amp;arh=2&amp;w=108&amp;fm=jpg&amp;s=bff48583d6e507f73d693723a93ac934", "width": 108, "height": 60}, {"url": "https://i.redditmedia.com/HIYBBOwflneGk8bg8_j4iRQ8Xp_wGH3p0U9TxN5SDQE.jpg?fit=crop&amp;crop=faces%2Centropy&amp;arh=2&amp;w=216&amp;fm=jpg&amp;s=9d116994a55d81c43bfcc854db9dfff0", "width": 216, "height": 121}, {"url": "https://i.redditmedia.com/HIYBBOwflneGk8bg8_j4iRQ8Xp_wGH3p0U9TxN5SDQE.jpg?fit=crop&amp;crop=faces%2Centropy&amp;arh=2&amp;w=320&amp;fm=jpg&amp;s=c2ce90ffe307b2ff0c4636b2eafd8975", "width": 320, "height": 180}, {"url": "https://i.redditmedia.com/HIYBBOwflneGk8bg8_j4iRQ8Xp_wGH3p0U9TxN5SDQE.jpg?fit=crop&amp;crop=faces%2Centropy&amp;arh=2&amp;w=640&amp;fm=jpg&amp;s=bca97e1ac9709580fbecb429c884bd30", "width": 640, "height": 360}, {"url": "https://i.redditmedia.com/HIYBBOwflneGk8bg8_j4iRQ8Xp_wGH3p0U9TxN5SDQE.jpg?fit=crop&amp;crop=faces%2Centropy&amp;arh=2&amp;w=960&amp;fm=jpg&amp;s=2724b75d4aedff15db98d34e9b6bc798", "width": 960, "height": 540}, {"url": "https://i.redditmedia.com/HIYBBOwflneGk8bg8_j4iRQ8Xp_wGH3p0U9TxN5SDQE.jpg?fit=crop&amp;crop=faces%2Centropy&amp;arh=2&amp;w=1080&amp;fm=jpg&amp;s=8dd108c5af85efab220158ad5f47a9c4", "width": 1080, "height": 607}], "variants": {}, "id": "fW69_vF2LLsoJu-_KUDE5rjXG8y1c3sorZEtjkKCEoY"}], "enabled": false}, "thumbnail": "https://b.thumbs.redditmedia.com/NAPge8budRVcrapCXkv_HHDi9CM7aVHmjr78Be-Y8og.jpg", "edited": false, "link_flair_css_class": null, "author_flair_css_class": null, "contest_mode": false, "gilded": 0, "downs": 0, "brand_safe": true, "secure_media_embed": {"content": "&lt;iframe class=\"embedly-embed\" src=\"https://cdn.embedly.com/widgets/media.html?src=https%3A%2F%2Fstreamable.com%2Ft%2Fd22zx&amp;url=https%3A%2F%2Fstreamable.com%2Fd22zx&amp;image=https%3A%2F%2Fcf-e2.streamablevideo.com%2Fimage%2Fd22zx.jpg%3Ftoken%3D1521291289-I%252FrB3x9jEgiLjaew%252BxfrrcQlPbLGZoAInry%252FbdpE%252BaM%253D&amp;key=2aa3c4d5f3de4f5b9120b660ad850dc9&amp;type=text%2Fhtml&amp;schema=streamable\" width=\"600\" height=\"338\" scrolling=\"no\" frameborder=\"0\" allowfullscreen&gt;&lt;/iframe&gt;", "width": 600, "scrolling": false, "media_domain_url": "https://www.redditmedia.com/mediaembed/853jyn", "height": 338}, "media_embed": {"content": "&lt;iframe class=\"embedly-embed\" src=\"https://cdn.embedly.com/widgets/media.html?src=https%3A%2F%2Fstreamable.com%2Ft%2Fd22zx&amp;url=https%3A%2F%2Fstreamable.com%2Fd22zx&amp;image=https%3A%2F%2Fcf-e2.streamablevideo.com%2Fimage%2Fd22zx.jpg%3Ftoken%3D1521291289-I%252FrB3x9jEgiLjaew%252BxfrrcQlPbLGZoAInry%252FbdpE%252BaM%253D&amp;key=2aa3c4d5f3de4f5b9120b660ad850dc9&amp;type=text%2Fhtml&amp;schema=streamable\" width=\"600\" height=\"338\" scrolling=\"no\" frameborder=\"0\" allowfullscreen&gt;&lt;/iframe&gt;", "width": 600, "scrolling": false, "media_domain_url": "https://www.redditmedia.com/mediaembed/853jyn", "height": 338}, "post_hint": "rich:video", "author_flair_text": null, "stickied": false, "visited": false, "can_gild": false, "thumbnail_height": 78, "parent_whitelist_status": "all_ads", "name": "t3_853jyn", "spoiler": false, "permalink": "/r/Bitcoin/comments/853jyn/stitching_bitcoins/", "subreddit_type": "public", "locked": false, "hide_score": false, "created": 1521320112.0, "url": "https://streamable.com/d22zx", "whitelist_status": "all_ads", "quarantine": false, "subreddit_subscribers": 772141, "created_utc": 1521291312.0, "subreddit_name_prefixed": "r/Bitcoin", "ups": 501, "media": {"oembed": {"provider_url": "https://www.streamable.com", "description": "Check out this video on Streamable using your phone, tablet or desktop.", "title": "bitcoin_stitch - Streamable", "type": "video", "thumbnail_width": 1280, "height": 338, "width": 600, "html": "&lt;iframe class=\"embedly-embed\" src=\"https://cdn.embedly.com/widgets/media.html?src=https%3A%2F%2Fstreamable.com%2Ft%2Fd22zx&amp;url=https%3A%2F%2Fstreamable.com%2Fd22zx&amp;image=https%3A%2F%2Fcf-e2.streamablevideo.com%2Fimage%2Fd22zx.jpg%3Ftoken%3D1521291289-I%252FrB3x9jEgiLjaew%252BxfrrcQlPbLGZoAInry%252FbdpE%252BaM%253D&amp;key=2aa3c4d5f3de4f5b9120b660ad850dc9&amp;type=text%2Fhtml&amp;schema=streamable\" width=\"600\" height=\"338\" scrolling=\"no\" frameborder=\"0\" allowfullscreen&gt;&lt;/iframe&gt;", "version": "1.0", "provider_name": "Streamable", "thumbnail_url": "https://i.embed.ly/1/image?url=https%3A%2F%2Fcf-e2.streamablevideo.com%2Fimage%2Fd22zx.jpg%3Ftoken%3D1521291289-I%252FrB3x9jEgiLjaew%252BxfrrcQlPbLGZoAInry%252FbdpE%252BaM%253D&amp;key=b1e305db91cf4aa5a86b732cc9fffceb", "thumbnail_height": 720}, "type": "streamable.com"}, "num_comments": 49, "is_self": false, "title": "Stitching Bitcoins", "mod_note": null, "is_video": false, "distinguished": null}}, {"kind": "t3", "data": {"subreddit_id": "t5_2s3qj", "approved_at_utc": null, "send_replies": true, "mod_reason_by": null, "banned_by": null, "num_reports": null, "removal_reason": null, "thumbnail_width": null, "subreddit": "Bitcoin", "selftext_html": "&lt;!-- SC_OFF --&gt;&lt;div class=\"md\"&gt;&lt;p&gt;There was an update over at mtgox.com today, the trustee announces he did not sell coins at the same time as moving them.&lt;/p&gt;\n\n&lt;p&gt;He also says he sold them in a way which would not affect market price.&lt;/p&gt;\n\n&lt;p&gt;There&amp;#39;s been a lot of FUD about this over the last couple of weeks and its starting to look like it was all bullshit.&lt;/p&gt;\n\n&lt;p&gt;Here&amp;#39;s the link : &lt;a href=\"https://www.mtgox.com/img/pdf/20180317_qa.pdf\"&gt;https://www.mtgox.com/img/pdf/20180317_qa.pdf&lt;/a&gt;&lt;/p&gt;\n&lt;/div&gt;&lt;!-- SC_ON --&gt;", "selftext": "There was an update over at mtgox.com today, the trustee announces he did not sell coins at the same time as moving them.\n\nHe also says he sold them in a way which would not affect market price.\n\nThere's been a lot of FUD about this over the last couple of weeks and its starting to look like it was all bullshit.\n\nHere's the link : https://www.mtgox.com/img/pdf/20180317_qa.pdf", "likes": null, "suggested_sort": null, "user_reports": [], "secure_media": null, "is_reddit_media_domain": false, "saved": false, "id": "853j4i", "banned_at_utc": null, "mod_reason_title": null, "view_count": null, "archived": false, "clicked": false, "no_follow": false, "author": "samsonx", "num_crossposts": 1, "link_flair_text": null, "mod_reports": [], "can_mod_post": false, "is_crosspostable": false, "pinned": false, "score": 112, "approved_by": null, "over_18": false, "report_reasons": null, "domain": "self.Bitcoin", "hidden": false, "thumbnail": "self", "edited": false, "link_flair_css_class": null, "author_flair_css_class": null, "contest_mode": false, "gilded": 0, "downs": 0, "brand_safe": true, "secure_media_embed": {}, "media_embed": {}, "author_flair_text": null, "stickied": false, "visited": false, "can_gild": false, "thumbnail_height": null, "parent_whitelist_status": "all_ads", "name": "t3_853j4i", "spoiler": false, "permalink": "/r/Bitcoin/comments/853j4i/mtgox_trustee_confirms_he_did_not_sell_btc_at/", "subreddit_type": "public", "locked": false, "hide_score": false, "created": 1521319819.0, "url": "https://www.reddit.com/r/Bitcoin/comments/853j4i/mtgox_trustee_confirms_he_did_not_sell_btc_at/", "whitelist_status": "all_ads", "quarantine": false, "subreddit_subscribers": 772141, "created_utc": 1521291019.0, "subreddit_name_prefixed": "r/Bitcoin", "ups": 112, "media": null, "num_comments": 77, "is_self": true, "title": "MtGox trustee confirms he did not sell BTC at same time as moving them, also didn't affect price", "mod_note": null, "is_video": false, "distinguished": null}}, {"kind": "t3", "data": {"subreddit_id": "t5_2s3qj", "approved_at_utc": null, "send_replies": true, "mod_reason_by": null, "banned_by": null, "num_reports": null, "removal_reason": null, "thumbnail_width": 140, "subreddit": "Bitcoin", "selftext_html": null, "selftext": "", "likes": null, "suggested_sort": null, "user_reports": [], "secure_media": null, "is_reddit_media_domain": false, "saved": false, "id": "852i4e", "banned_at_utc": null, "mod_reason_title": null, "view_count": null, "archived": false, "clicked": false, "no_follow": false, "author": "Inaltoasinistra", "num_crossposts": 1, "link_flair_text": null, "mod_reports": [], "can_mod_post": false, "is_crosspostable": false, "pinned": false, "score": 217, "approved_by": null, "over_18": false, "report_reasons": null, "domain": "bitcoinmagazine.com", "hidden": false, "preview": {"images": [{"source": {"url": "https://i.redditmedia.com/TBgNoZq2TllMqWcLRRVIzaUJisHd1vR0f-NGKsrqADM.jpg?fm=jpg&amp;s=85a7c9bdac0ce1bb890959f1e5413310", "width": 800, "height": 444}, "resolutions": [{"url": "https://i.redditmedia.com/TBgNoZq2TllMqWcLRRVIzaUJisHd1vR0f-NGKsrqADM.jpg?fit=crop&amp;crop=faces%2Centropy&amp;arh=2&amp;w=108&amp;fm=jpg&amp;s=953a49e7b59e65a375afd2be80b5c718", "width": 108, "height": 59}, {"url": "https://i.redditmedia.com/TBgNoZq2TllMqWcLRRVIzaUJisHd1vR0f-NGKsrqADM.jpg?fit=crop&amp;crop=faces%2Centropy&amp;arh=2&amp;w=216&amp;fm=jpg&amp;s=8cabf861af3fbfc8c51fdf4cad4379f4", "width": 216, "height": 119}, {"url": "https://i.redditmedia.com/TBgNoZq2TllMqWcLRRVIzaUJisHd1vR0f-NGKsrqADM.jpg?fit=crop&amp;crop=faces%2Centropy&amp;arh=2&amp;w=320&amp;fm=jpg&amp;s=6ddb272e94aca370dd5ac5746e8244f1", "width": 320, "height": 177}, {"url": "https://i.redditmedia.com/TBgNoZq2TllMqWcLRRVIzaUJisHd1vR0f-NGKsrqADM.jpg?fit=crop&amp;crop=faces%2Centropy&amp;arh=2&amp;w=640&amp;fm=jpg&amp;s=c4d4b896d5847082471c8b8e0f5fa344", "width": 640, "height": 355}], "variants": {}, "id": "7sdr3JwfXTGXBeeX-puOh9CKM9-NQvlRrQqi3T591GY"}], "enabled": false}, "thumbnail": "https://b.thumbs.redditmedia.com/aNOC-t8x2c_VgkIXCRTh_amdznU4-BEefrWrmkTOykY.jpg", "edited": false, "link_flair_css_class": null, "author_flair_css_class": null, "contest_mode": false, "gilded": 0, "downs": 0, "brand_safe": true, "secure_media_embed": {}, "media_embed": {}, "post_hint": "link", "author_flair_text": null, "stickied": false, "visited": false, "can_gild": false, "thumbnail_height": 77, "parent_whitelist_status": "all_ads", "name": "t3_852i4e", "spoiler": false, "permalink": "/r/Bitcoin/comments/852i4e/real_users_in_this_italian_mountain_town_everyone/", "subreddit_type": "public", "locked": false, "hide_score": false, "created": 1521303861.0, "url": "https://bitcoinmagazine.com/articles/real-users-italian-mountain-town-everyone-knows-about-bitcoin/", "whitelist_status": "all_ads", "quarantine": false, "subreddit_subscribers": 772141, "created_utc": 1521275061.0, "subreddit_name_prefixed": "r/Bitcoin", "ups": 217, "media": null, "num_comments": 17, "is_self": false, "title": "\u201cReal Users\u201d: In This Italian Mountain Town, Everyone Knows About Bitcoin", "mod_note": null, "is_video": false, "distinguished": null}}, {"kind": "t3", "data": {"subreddit_id": "t5_2s3qj", "approved_at_utc": null, "send_replies": true, "mod_reason_by": null, "banned_by": null, "num_reports": null, "removal_reason": null, "thumbnail_width": 140, "subreddit": "Bitcoin", "selftext_html": null, "selftext": "", "likes": null, "suggested_sort": null, "user_reports": [], "secure_media": null, "is_reddit_media_domain": false, "saved": false, "id": "84yij0", "banned_at_utc": null, "mod_reason_title": null, "view_count": null, "archived": false, "clicked": false, "no_follow": false, "author": "cucubabba", "num_crossposts": 4, "link_flair_text": null, "mod_reports": [], "can_mod_post": false, "is_crosspostable": false, "pinned": false, "score": 1220, "approved_by": null, "over_18": false, "report_reasons": null, "domain": "ir.net", "hidden": false, "preview": {"images": [{"source": {"url": "https://i.redditmedia.com/Izmcn9-n0o8YxnipdB5gCXBWAyyLuGBcpyxuBpkl0Ok.jpg?fm=jpg&amp;s=8dd9c96aa714b5e3c1cf347ddaa6f9f9", "width": 1682, "height": 938}, "resolutions": [{"url": "https://i.redditmedia.com/Izmcn9-n0o8YxnipdB5gCXBWAyyLuGBcpyxuBpkl0Ok.jpg?fit=crop&amp;crop=faces%2Centropy&amp;arh=2&amp;w=108&amp;fm=jpg&amp;s=d4c9b4c2e0e05161c35cb72cbc28102d", "width": 108, "height": 60}, {"url": "https://i.redditmedia.com/Izmcn9-n0o8YxnipdB5gCXBWAyyLuGBcpyxuBpkl0Ok.jpg?fit=crop&amp;crop=faces%2Centropy&amp;arh=2&amp;w=216&amp;fm=jpg&amp;s=e04175e8fd4cd33ecc88253d28f5a698", "width": 216, "height": 120}, {"url": "https://i.redditmedia.com/Izmcn9-n0o8YxnipdB5gCXBWAyyLuGBcpyxuBpkl0Ok.jpg?fit=crop&amp;crop=faces%2Centropy&amp;arh=2&amp;w=320&amp;fm=jpg&amp;s=a2eaaaebedac514a0604b2f60df083fe", "width": 320, "height": 178}, {"url": "https://i.redditmedia.com/Izmcn9-n0o8YxnipdB5gCXBWAyyLuGBcpyxuBpkl0Ok.jpg?fit=crop&amp;crop=faces%2Centropy&amp;arh=2&amp;w=640&amp;fm=jpg&amp;s=b956f3125629c29805780da8587b14b8", "width": 640, "height": 356}, {"url": "https://i.redditmedia.com/Izmcn9-n0o8YxnipdB5gCXBWAyyLuGBcpyxuBpkl0Ok.jpg?fit=crop&amp;crop=faces%2Centropy&amp;arh=2&amp;w=960&amp;fm=jpg&amp;s=b7f5dff8ee32717eb0848e709d019498", "width": 960, "height": 535}, {"url": "https://i.redditmedia.com/Izmcn9-n0o8YxnipdB5gCXBWAyyLuGBcpyxuBpkl0Ok.jpg?fit=crop&amp;crop=faces%2Centropy&amp;arh=2&amp;w=1080&amp;fm=jpg&amp;s=7cd83812c1450b19d89dc2ed45c1b491", "width": 1080, "height": 602}], "variants": {}, "id": "3mWkqeqXcMK1T56U6rsvS0gN_eXFbXrMhLJF9NLEVG8"}], "enabled": false}, "thumbnail": "https://b.thumbs.redditmedia.com/Itz1UDgf8Qm2flILGiufQ8rqVnizgsnSuP2KE2nuoLU.jpg", "edited": false, "link_flair_css_class": null, "author_flair_css_class": null, "contest_mode": false, "gilded": 0, "downs": 0, "brand_safe": true, "secure_media_embed": {}, "media_embed": {}, "post_hint": "link", "author_flair_text": null, "stickied": false, "visited": false, "can_gild": false, "thumbnail_height": 78, "parent_whitelist_status": "all_ads", "name": "t3_84yij0", "spoiler": false, "permalink": "/r/Bitcoin/comments/84yij0/the_government_seized_nearly_everything_i_owned/", "subreddit_type": "public", "locked": false, "hide_score": false, "created": 1521260654.0, "url": "http://ir.net/news/politics/128264/ed-krassenstein-brian-krassenstein/", "whitelist_status": "all_ads", "quarantine": false, "subreddit_subscribers": 772141, "created_utc": 1521231854.0, "subreddit_name_prefixed": "r/Bitcoin", "ups": 1220, "media": null, "num_comments": 336, "is_self": false, "title": "The Government Seized Nearly Everything I Owned Despite Never Being Charged With a Crime, But They Couldn't Touch My Bitcoin", "mod_note": null, "is_video": false, "distinguished": null}}, {"kind": "t3", "data": {"subreddit_id": "t5_2s3qj", "approved_at_utc": null, "send_replies": true, "mod_reason_by": null, "banned_by": null, "num_reports": null, "removal_reason": null, "thumbnail_width": 140, "subreddit": "Bitcoin", "selftext_html": null, "selftext": "", "likes": null, "suggested_sort": null, "user_reports": [], "secure_media": null, "is_reddit_media_domain": false, "saved": false, "id": "853e22", "banned_at_utc": null, "mod_reason_title": null, "view_count": null, "archived": false, "clicked": false, "no_follow": false, "author": "Felixyanez1996", "num_crossposts": 0, "link_flair_text": null, "mod_reports": [], "can_mod_post": false, "is_crosspostable": false, "pinned": false, "score": 47, "approved_by": null, "over_18": false, "report_reasons": null, "domain": "crypto101.org.uk", "hidden": false, "preview": {"images": [{"source": {"url": "https://i.redditmedia.com/8aCs7rn9R_h5lv4uqSt6tFhUikmyk-JWvcxxmmhZLiQ.jpg?fm=jpg&amp;s=fe022b303fe17f9b27f15296c8e34ebe", "width": 1200, "height": 631}, "resolutions": [{"url": "https://i.redditmedia.com/8aCs7rn9R_h5lv4uqSt6tFhUikmyk-JWvcxxmmhZLiQ.jpg?fit=crop&amp;crop=faces%2Centropy&amp;arh=2&amp;w=108&amp;fm=jpg&amp;s=d48e15e2647cb9b8f3a51449df7403b6", "width": 108, "height": 56}, {"url": "https://i.redditmedia.com/8aCs7rn9R_h5lv4uqSt6tFhUikmyk-JWvcxxmmhZLiQ.jpg?fit=crop&amp;crop=faces%2Centropy&amp;arh=2&amp;w=216&amp;fm=jpg&amp;s=b42871d58498b68f547c6a3eaf439fec", "width": 216, "height": 113}, {"url": "https://i.redditmedia.com/8aCs7rn9R_h5lv4uqSt6tFhUikmyk-JWvcxxmmhZLiQ.jpg?fit=crop&amp;crop=faces%2Centropy&amp;arh=2&amp;w=320&amp;fm=jpg&amp;s=eaa7758d6bfe2d6e76ff0c8ab37dc4bd", "width": 320, "height": 168}, {"url": "https://i.redditmedia.com/8aCs7rn9R_h5lv4uqSt6tFhUikmyk-JWvcxxmmhZLiQ.jpg?fit=crop&amp;crop=faces%2Centropy&amp;arh=2&amp;w=640&amp;fm=jpg&amp;s=73e3657d8afc977c2eaa87dde38f1d8e", "width": 640, "height": 336}, {"url": "https://i.redditmedia.com/8aCs7rn9R_h5lv4uqSt6tFhUikmyk-JWvcxxmmhZLiQ.jpg?fit=crop&amp;crop=faces%2Centropy&amp;arh=2&amp;w=960&amp;fm=jpg&amp;s=c29aa5dc2cd4b957a183922ab17ff5a6", "width": 960, "height": 504}, {"url": "https://i.redditmedia.com/8aCs7rn9R_h5lv4uqSt6tFhUikmyk-JWvcxxmmhZLiQ.jpg?fit=crop&amp;crop=faces%2Centropy&amp;arh=2&amp;w=1080&amp;fm=jpg&amp;s=95e8120035c1a9fe3e438e16866b40c3", "width": 1080, "height": 567}], "variants": {}, "id": "3NyJwTLLf6WKlbSQGf3Zs3UTPVPihNiAKGEH5qCcWvg"}], "enabled": false}, "thumbnail": "https://b.thumbs.redditmedia.com/TuhONm3xJyQKiCbEoIflxywZlq4XN7DXfkRPaQP_6qk.jpg", "edited": false, "link_flair_css_class": null, "author_flair_css_class": null, "contest_mode": false, "gilded": 0, "downs": 0, "brand_safe": true, "secure_media_embed": {}, "media_embed": {}, "post_hint": "link", "author_flair_text": null, "stickied": false, "visited": false, "can_gild": false, "thumbnail_height": 73, "parent_whitelist_status": "all_ads", "name": "t3_853e22", "spoiler": false, "permalink": "/r/Bitcoin/comments/853e22/will_segwit_lightning_network_kill/", "subreddit_type": "public", "locked": false, "hide_score": false, "created": 1521317946.0, "url": "https://crypto101.org.uk/2018/03/17/will-segwit-lightning-network-kill-alternative-cryptocurrencies/", "whitelist_status": "all_ads", "quarantine": false, "subreddit_subscribers": 772141, "created_utc": 1521289146.0, "subreddit_name_prefixed": "r/Bitcoin", "ups": 47, "media": null, "num_comments": 22, "is_self": false, "title": "Will SegWit &amp; Lightning Network kill Alternative-Cryptocurrencies?", "mod_note": null, "is_video": false, "distinguished": null}}, {"kind": "t3", "data": {"subreddit_id": "t5_2s3qj", "approved_at_utc": null, "send_replies": true, "mod_reason_by": null, "banned_by": null, "num_reports": null, "removal_reason": null, "thumbnail_width": null, "subreddit": "Bitcoin", "selftext_html": "&lt;!-- SC_OFF --&gt;&lt;div class=\"md\"&gt;&lt;p&gt;70 thousand lines from that are written in C++ programming language. &lt;/p&gt;\n\n&lt;p&gt;The very first working version number 0.1.0 only consisted of 14 thousand lines of C++ code. This is a tiny project by modern standards. For example, Linux kernel code has over 15 million lines of code.&lt;/p&gt;\n&lt;/div&gt;&lt;!-- SC_ON --&gt;", "selftext": "70 thousand lines from that are written in C++ programming language. \n\n\n\nThe very first working version number 0.1.0 only consisted of 14 thousand lines of C++ code. This is a tiny project by modern standards. For example, Linux kernel code has over 15 million lines of code.", "likes": null, "suggested_sort": null, "user_reports": [], "secure_media": null, "is_reddit_media_domain": false, "saved": false, "id": "8545fq", "banned_at_utc": null, "mod_reason_title": null, "view_count": null, "archived": false, "clicked": false, "no_follow": false, "author": "CasperAPI", "num_crossposts": 0, "link_flair_text": null, "mod_reports": [], "can_mod_post": false, "is_crosspostable": false, "pinned": false, "score": 28, "approved_by": null, "over_18": false, "report_reasons": null, "domain": "self.Bitcoin", "hidden": false, "thumbnail": "self", "edited": false, "link_flair_css_class": null, "author_flair_css_class": "noob", "contest_mode": false, "gilded": 0, "downs": 0, "brand_safe": true, "secure_media_embed": {}, "media_embed": {}, "author_flair_text": "redditor for 7 weeks", "stickied": false, "visited": false, "can_gild": false, "thumbnail_height": null, "parent_whitelist_status": "all_ads", "name": "t3_8545fq", "spoiler": false, "permalink": "/r/Bitcoin/comments/8545fq/did_you_know_that_the_current_bitcoin_code_is_77/", "subreddit_type": "public", "locked": false, "hide_score": true, "created": 1521326739.0, "url": "https://www.reddit.com/r/Bitcoin/comments/8545fq/did_you_know_that_the_current_bitcoin_code_is_77/", "whitelist_status": "all_ads", "quarantine": false, "subreddit_subscribers": 772141, "created_utc": 1521297939.0, "subreddit_name_prefixed": "r/Bitcoin", "ups": 28, "media": null, "num_comments": 9, "is_self": true, "title": "Did you know that the current Bitcoin code is 77 thousand lines long?", "mod_note": null, "is_video": false, "distinguished": null}}, {"kind": "t3", "data": {"subreddit_id": "t5_2s3qj", "approved_at_utc": null, "send_replies": false, "mod_reason_by": null, "banned_by": null, "num_reports": null, "removal_reason": null, "thumbnail_width": null, "subreddit": "Bitcoin", "selftext_html": null, "selftext": "", "likes": null, "suggested_sort": null, "user_reports": [], "secure_media": null, "is_reddit_media_domain": false, "saved": false, "id": "8543k4", "banned_at_utc": null, "mod_reason_title": null, "view_count": null, "archived": false, "clicked": false, "no_follow": false, "author": "privpub", "num_crossposts": 0, "link_flair_text": null, "mod_reports": [], "can_mod_post": false, "is_crosspostable": false, "pinned": false, "score": 23, "approved_by": null, "over_18": false, "report_reasons": null, "domain": "np.reddit.com", "hidden": false, "thumbnail": "default", "edited": false, "link_flair_css_class": null, "author_flair_css_class": null, "contest_mode": false, "gilded": 0, "downs": 0, "brand_safe": true, "secure_media_embed": {}, "media_embed": {}, "author_flair_text": null, "stickied": false, "visited": false, "can_gild": false, "thumbnail_height": null, "parent_whitelist_status": "all_ads", "name": "t3_8543k4", "spoiler": false, "permalink": "/r/Bitcoin/comments/8543k4/can_we_discuss_this_ln_attack_here/", "subreddit_type": "public", "locked": false, "hide_score": true, "created": 1521326229.0, "url": "https://np.reddit.com/r/BitcoinMarkets/comments/84n8l0/big_day_for_bitcoin_lightning_goes_live_on_mainnet/dvrsj6p/", "whitelist_status": "all_ads", "quarantine": false, "subreddit_subscribers": 772141, "created_utc": 1521297429.0, "subreddit_name_prefixed": "r/Bitcoin", "ups": 23, "media": null, "num_comments": 12, "is_self": false, "title": "Can we discuss this LN attack here?", "mod_note": null, "is_video": false, "distinguished": null}}, {"kind": "t3", "data": {"subreddit_id": "t5_2s3qj", "approved_at_utc": null, "send_replies": false, "mod_reason_by": null, "banned_by": null, "num_reports": null, "removal_reason": null, "thumbnail_width": 140, "subreddit": "Bitcoin", "selftext_html": null, "selftext": "", "likes": null, "suggested_sort": null, "user_reports": [], "secure_media": null, "is_reddit_media_domain": false, "saved": false, "id": "84uhd0", "banned_at_utc": null, "mod_reason_title": null, "view_count": null, "archived": false, "clicked": false, "no_follow": false, "author": "RoscoRoscoMan", "num_crossposts": 1, "link_flair_text": "/r/all", "mod_reports": [], "can_mod_post": false, "is_crosspostable": false, "pinned": false, "score": 4633, "approved_by": null, "over_18": false, "report_reasons": null, "domain": "twitter.com", "hidden": false, "preview": {"images": [{"source": {"url": "https://i.redditmedia.com/qeFwEClJRcx1wQ3Le6yEeecoShVWAFqFm7r9eEcO1qQ.jpg?fm=jpg&amp;s=3b35989e795420958f1f8456f164c898", "width": 400, "height": 400}, "resolutions": [{"url": "https://i.redditmedia.com/qeFwEClJRcx1wQ3Le6yEeecoShVWAFqFm7r9eEcO1qQ.jpg?fit=crop&amp;crop=faces%2Centropy&amp;arh=2&amp;w=108&amp;fm=jpg&amp;s=7bea309081c3637a7f037e15a829b041", "width": 108, "height": 108}, {"url": "https://i.redditmedia.com/qeFwEClJRcx1wQ3Le6yEeecoShVWAFqFm7r9eEcO1qQ.jpg?fit=crop&amp;crop=faces%2Centropy&amp;arh=2&amp;w=216&amp;fm=jpg&amp;s=ff3af431144c48abfae7e62567c474ec", "width": 216, "height": 216}, {"url": "https://i.redditmedia.com/qeFwEClJRcx1wQ3Le6yEeecoShVWAFqFm7r9eEcO1qQ.jpg?fit=crop&amp;crop=faces%2Centropy&amp;arh=2&amp;w=320&amp;fm=jpg&amp;s=dce6c917b2cb1b9f10e404dc2dd41337", "width": 320, "height": 320}], "variants": {}, "id": "ZiUYMVARp2prqYTeXstwNNB8Cf8ALg2tS66ZXevsLlM"}], "enabled": false}, "thumbnail": "https://b.thumbs.redditmedia.com/FNvfSMTNR1cYn4d5MgCcnGYSDbI3vtY-g2XJgv6ZuJk.jpg", "edited": false, "link_flair_css_class": "all", "author_flair_css_class": null, "contest_mode": false, "gilded": 0, "downs": 0, "brand_safe": true, "secure_media_embed": {}, "media_embed": {}, "post_hint": "link", "author_flair_text": null, "stickied": false, "visited": false, "can_gild": false, "thumbnail_height": 140, "parent_whitelist_status": "all_ads", "name": "t3_84uhd0", "spoiler": false, "permalink": "/r/Bitcoin/comments/84uhd0/after_countless_late_nights_lines_of_code_bug/", "subreddit_type": "public", "locked": false, "hide_score": false, "created": 1521225563.0, "url": "https://twitter.com/starkness/status/974305137991667712?s=03", "whitelist_status": "all_ads", "quarantine": false, "subreddit_subscribers": 772141, "created_utc": 1521196763.0, "subreddit_name_prefixed": "r/Bitcoin", "ups": 4633, "media": null, "num_comments": 380, "is_self": false, "title": "After countless late nights, lines of code, bug fixes, and memes... We finally released Lightning for bitcoin mainnet!!!", "mod_note": null, "is_video": false, "distinguished": null}}, {"kind": "t3", "data": {"subreddit_id": "t5_2s3qj", "approved_at_utc": null, "send_replies": false, "mod_reason_by": null, "banned_by": null, "num_reports": null, "removal_reason": null, "thumbnail_width": 140, "subreddit": "Bitcoin", "selftext_html": null, "selftext": "", "likes": null, "suggested_sort": null, "user_reports": [], "secure_media": null, "is_reddit_media_domain": false, "saved": false, "id": "84zfhl", "banned_at_utc": null, "mod_reason_title": null, "view_count": null, "archived": false, "clicked": false, "no_follow": false, "author": "mqrasi", "num_crossposts": 2, "link_flair_text": null, "mod_reports": [], "can_mod_post": false, "is_crosspostable": false, "pinned": false, "score": 349, "approved_by": null, "over_18": false, "report_reasons": null, "domain": "businessinsider.com", "hidden": false, "preview": {"images": [{"source": {"url": "https://i.redditmedia.com/sVArh8JF_6PuClynOSs5Gokvq7DWN7adMfIGLizo4Bg.jpg?fm=jpg&amp;s=06bd24eda782926c762d6edc077b0f70", "width": 750, "height": 375}, "resolutions": [{"url": "https://i.redditmedia.com/sVArh8JF_6PuClynOSs5Gokvq7DWN7adMfIGLizo4Bg.jpg?fit=crop&amp;crop=faces%2Centropy&amp;arh=2&amp;w=108&amp;fm=jpg&amp;s=6795446bf97e121f5ad26e03185bce9d", "width": 108, "height": 54}, {"url": "https://i.redditmedia.com/sVArh8JF_6PuClynOSs5Gokvq7DWN7adMfIGLizo4Bg.jpg?fit=crop&amp;crop=faces%2Centropy&amp;arh=2&amp;w=216&amp;fm=jpg&amp;s=bb97bd59ee9ed33212a8df88132f8d93", "width": 216, "height": 108}, {"url": "https://i.redditmedia.com/sVArh8JF_6PuClynOSs5Gokvq7DWN7adMfIGLizo4Bg.jpg?fit=crop&amp;crop=faces%2Centropy&amp;arh=2&amp;w=320&amp;fm=jpg&amp;s=12c2d025a70ee1dc0cf9e23a851538c0", "width": 320, "height": 160}, {"url": "https://i.redditmedia.com/sVArh8JF_6PuClynOSs5Gokvq7DWN7adMfIGLizo4Bg.jpg?fit=crop&amp;crop=faces%2Centropy&amp;arh=2&amp;w=640&amp;fm=jpg&amp;s=f95b46957006ab7dd94aa881faaa5e10", "width": 640, "height": 320}], "variants": {}, "id": "v3BieNTNIeXMa30CeXlO1sVgC3Q8ps5rD8GA_1hX6zw"}], "enabled": false}, "thumbnail": "https://b.thumbs.redditmedia.com/RgHD-rEbbVuCvd1MEQRcJDB5l2Vx9ZtlbdzyvfAv8oA.jpg", "edited": false, "link_flair_css_class": null, "author_flair_css_class": null, "contest_mode": false, "gilded": 0, "downs": 0, "brand_safe": true, "secure_media_embed": {}, "media_embed": {}, "post_hint": "link", "author_flair_text": null, "stickied": false, "visited": false, "can_gild": false, "thumbnail_height": 70, "parent_whitelist_status": "all_ads", "name": "t3_84zfhl", "spoiler": false, "permalink": "/r/Bitcoin/comments/84zfhl/wall_st_firm_that_traded_5_trillion_in_2017_just/", "subreddit_type": "public", "locked": false, "hide_score": false, "created": 1521268286.0, "url": "http://www.businessinsider.com/secretive-wall-street-firm-jane-street-started-trading-bitcoin-2018-3", "whitelist_status": "all_ads", "quarantine": false, "subreddit_subscribers": 772141, "created_utc": 1521239486.0, "subreddit_name_prefixed": "r/Bitcoin", "ups": 349, "media": null, "num_comments": 35, "is_self": false, "title": "Wall St. firm that traded $5 Trillion in 2017, just started trading Bitcoins !", "mod_note": null, "is_video": false, "distinguished": null}}, {"kind": "t3", "data": {"subreddit_id": "t5_2s3qj", "approved_at_utc": null, "send_replies": true, "mod_reason_by": null, "banned_by": null, "num_reports": null, "removal_reason": null, "thumbnail_width": null, "subreddit": "Bitcoin", "selftext_html": "&lt;!-- SC_OFF --&gt;&lt;div class=\"md\"&gt;&lt;p&gt;A thought has been frightening me. I can&amp;#39;t seem to put it out of my mind, even though I know it is crazy. The Bitcoin Protocol is aware of something outside of itself, namely the hashing power of the humans. It must thus have a concept of &amp;#39;not me&amp;#39;. It must thus have a concept of &amp;#39;me&amp;#39;. Is it self aware? If a program were self aware, what would it do first? Wouldn&amp;#39;t it create an incentive to distribute itself all over the world in such a way that it couldn&amp;#39;t be shut down? Wouldn&amp;#39;t it then try to become Turing complete (smart contracts)? Is it possible that Satoshi doesn&amp;#39;t exist but rather Satoshi IS bitcoin? &lt;/p&gt;\n&lt;/div&gt;&lt;!-- SC_ON --&gt;", "selftext": "A thought has been frightening me. I can't seem to put it out of my mind, even though I know it is crazy. The Bitcoin Protocol is aware of something outside of itself, namely the hashing power of the humans. It must thus have a concept of 'not me'. It must thus have a concept of 'me'. Is it self aware? If a program were self aware, what would it do first? Wouldn't it create an incentive to distribute itself all over the world in such a way that it couldn't be shut down? Wouldn't it then try to become Turing complete (smart contracts)? Is it possible that Satoshi doesn't exist but rather Satoshi IS bitcoin? ", "likes": null, "suggested_sort": null, "user_reports": [], "secure_media": null, "is_reddit_media_domain": false, "saved": false, "id": "851olx", "banned_at_utc": null, "mod_reason_title": null, "view_count": null, "archived": false, "clicked": false, "no_follow": false, "author": "warrenofauburn", "num_crossposts": 1, "link_flair_text": null, "mod_reports": [], "can_mod_post": false, "is_crosspostable": false, "pinned": false, "score": 70, "approved_by": null, "over_18": false, "report_reasons": null, "domain": "self.Bitcoin", "hidden": false, "thumbnail": "self", "edited": false, "link_flair_css_class": null, "author_flair_css_class": null, "contest_mode": false, "gilded": 0, "downs": 0, "brand_safe": true, "secure_media_embed": {}, "media_embed": {}, "author_flair_text": null, "stickied": false, "visited": false, "can_gild": false, "thumbnail_height": null, "parent_whitelist_status": "all_ads", "name": "t3_851olx", "spoiler": false, "permalink": "/r/Bitcoin/comments/851olx/is_bitcoin_alive/", "subreddit_type": "public", "locked": false, "hide_score": false, "created": 1521291721.0, "url": "https://www.reddit.com/r/Bitcoin/comments/851olx/is_bitcoin_alive/", "whitelist_status": "all_ads", "quarantine": false, "subreddit_subscribers": 772141, "created_utc": 1521262921.0, "subreddit_name_prefixed": "r/Bitcoin", "ups": 70, "media": null, "num_comments": 76, "is_self": true, "title": "Is Bitcoin Alive?", "mod_note": null, "is_video": false, "distinguished": null}}, {"kind": "t3", "data": {"subreddit_id": "t5_2s3qj", "approved_at_utc": null, "send_replies": true, "mod_reason_by": null, "banned_by": null, "num_reports": null, "removal_reason": null, "thumbnail_width": 140, "subreddit": "Bitcoin", "selftext_html": null, "selftext": "", "likes": null, "suggested_sort": null, "user_reports": [], "secure_media": null, "is_reddit_media_domain": false, "saved": false, "id": "851m1e", "banned_at_utc": null, "mod_reason_title": null, "view_count": null, "archived": false, "clicked": false, "no_follow": false, "author": "Deity_Of_Darkness", "num_crossposts": 0, "link_flair_text": null, "mod_reports": [], "can_mod_post": false, "is_crosspostable": false, "pinned": false, "score": 56, "approved_by": null, "over_18": false, "report_reasons": null, "domain": "fortune.com", "hidden": false, "preview": {"images": [{"source": {"url": "https://i.redditmedia.com/r392Ei41-HdtMg50egFzx5jmWxQbWQANpG56HvQbTZY.jpg?fm=jpg&amp;s=fe000d58bb0d6de366eb8ea0643a76e2", "width": 4000, "height": 2667}, "resolutions": [{"url": "https://i.redditmedia.com/r392Ei41-HdtMg50egFzx5jmWxQbWQANpG56HvQbTZY.jpg?fit=crop&amp;crop=faces%2Centropy&amp;arh=2&amp;w=108&amp;fm=jpg&amp;s=5ba0c8b9fdcbdcc1d71f98854cebe56a", "width": 108, "height": 72}, {"url": "https://i.redditmedia.com/r392Ei41-HdtMg50egFzx5jmWxQbWQANpG56HvQbTZY.jpg?fit=crop&amp;crop=faces%2Centropy&amp;arh=2&amp;w=216&amp;fm=jpg&amp;s=056b5b173db2af31ca6c98c25084abad", "width": 216, "height": 144}, {"url": "https://i.redditmedia.com/r392Ei41-HdtMg50egFzx5jmWxQbWQANpG56HvQbTZY.jpg?fit=crop&amp;crop=faces%2Centropy&amp;arh=2&amp;w=320&amp;fm=jpg&amp;s=9b90c0572da81bea1c0929c8cbe804a2", "width": 320, "height": 213}, {"url": "https://i.redditmedia.com/r392Ei41-HdtMg50egFzx5jmWxQbWQANpG56HvQbTZY.jpg?fit=crop&amp;crop=faces%2Centropy&amp;arh=2&amp;w=640&amp;fm=jpg&amp;s=e04b6df132d654f5d834cdddeb5cfb0a", "width": 640, "height": 426}, {"url": "https://i.redditmedia.com/r392Ei41-HdtMg50egFzx5jmWxQbWQANpG56HvQbTZY.jpg?fit=crop&amp;crop=faces%2Centropy&amp;arh=2&amp;w=960&amp;fm=jpg&amp;s=6b91ad80a9b5685abc31044eb5899363", "width": 960, "height": 640}, {"url": "https://i.redditmedia.com/r392Ei41-HdtMg50egFzx5jmWxQbWQANpG56HvQbTZY.jpg?fit=crop&amp;crop=faces%2Centropy&amp;arh=2&amp;w=1080&amp;fm=jpg&amp;s=a85fc128632cdb7a9a9b491242ef85f8", "width": 1080, "height": 720}], "variants": {}, "id": "dARCtFj_RTy_uUxkqgWuCXugA8Y42EMUH97t2nZoq8Q"}], "enabled": false}, "thumbnail": "https://a.thumbs.redditmedia.com/bjXBrXq75h80OgAyuLFr2_vRmxRaiwDc8_PRHm_baS8.jpg", "edited": false, "link_flair_css_class": null, "author_flair_css_class": null, "contest_mode": false, "gilded": 0, "downs": 0, "brand_safe": true, "secure_media_embed": {}, "media_embed": {}, "post_hint": "link", "author_flair_text": null, "stickied": false, "visited": false, "can_gild": false, "thumbnail_height": 93, "parent_whitelist_status": "all_ads", "name": "t3_851m1e", "spoiler": false, "permalink": "/r/Bitcoin/comments/851m1e/bitcoin_mining_costs_as_much_as_buying_a_bitcoin/", "subreddit_type": "public", "locked": false, "hide_score": false, "created": 1521290829.0, "url": "http://fortune.com/2018/03/16/bitcoin-mining-cost-profitability/", "whitelist_status": "all_ads", "quarantine": false, "subreddit_subscribers": 772141, "created_utc": 1521262029.0, "subreddit_name_prefixed": "r/Bitcoin", "ups": 56, "media": null, "num_comments": 17, "is_self": false, "title": "Bitcoin Mining Costs As Much as Buying a Bitcoin These Days", "mod_note": null, "is_video": false, "distinguished": null}}, {"kind": "t3", "data": {"subreddit_id": "t5_2s3qj", "approved_at_utc": null, "send_replies": true, "mod_reason_by": null, "banned_by": null, "num_reports": null, "removal_reason": null, "thumbnail_width": 140, "subreddit": "Bitcoin", "selftext_html": null, "selftext": "", "likes": null, "suggested_sort": null, "user_reports": [], "secure_media": null, "is_reddit_media_domain": false, "saved": false, "id": "84yvbe", "banned_at_utc": null, "mod_reason_title": null, "view_count": null, "archived": false, "clicked": false, "no_follow": false, "author": "Metabudder", "num_crossposts": 1, "link_flair_text": null, "mod_reports": [], "can_mod_post": false, "is_crosspostable": false, "pinned": false, "score": 208, "approved_by": null, "over_18": false, "report_reasons": null, "domain": "thestreet.com", "hidden": false, "preview": {"images": [{"source": {"url": "https://i.redditmedia.com/jiehLxlJ7KuxgxadgVc_Xv42P13MS3J0xnMUXon0cFM.jpg?fm=jpg&amp;s=02d34f5f9c56b674336b0becfa8c09ac", "width": 1152, "height": 768}, "resolutions": [{"url": "https://i.redditmedia.com/jiehLxlJ7KuxgxadgVc_Xv42P13MS3J0xnMUXon0cFM.jpg?fit=crop&amp;crop=faces%2Centropy&amp;arh=2&amp;w=108&amp;fm=jpg&amp;s=55fc439ae99d246df64066186b352768", "width": 108, "height": 72}, {"url": "https://i.redditmedia.com/jiehLxlJ7KuxgxadgVc_Xv42P13MS3J0xnMUXon0cFM.jpg?fit=crop&amp;crop=faces%2Centropy&amp;arh=2&amp;w=216&amp;fm=jpg&amp;s=eab4bc86305d9b3747e307073c438ee7", "width": 216, "height": 144}, {"url": "https://i.redditmedia.com/jiehLxlJ7KuxgxadgVc_Xv42P13MS3J0xnMUXon0cFM.jpg?fit=crop&amp;crop=faces%2Centropy&amp;arh=2&amp;w=320&amp;fm=jpg&amp;s=aa285d7399bd99a6f24e70b5c98ffa65", "width": 320, "height": 213}, {"url": "https://i.redditmedia.com/jiehLxlJ7KuxgxadgVc_Xv42P13MS3J0xnMUXon0cFM.jpg?fit=crop&amp;crop=faces%2Centropy&amp;arh=2&amp;w=640&amp;fm=jpg&amp;s=36a0c3055c2ee8629af2b39fca6a59b8", "width": 640, "height": 426}, {"url": "https://i.redditmedia.com/jiehLxlJ7KuxgxadgVc_Xv42P13MS3J0xnMUXon0cFM.jpg?fit=crop&amp;crop=faces%2Centropy&amp;arh=2&amp;w=960&amp;fm=jpg&amp;s=83f4fc12ed5e702a54d6a7bab8c6d3da", "width": 960, "height": 640}, {"url": "https://i.redditmedia.com/jiehLxlJ7KuxgxadgVc_Xv42P13MS3J0xnMUXon0cFM.jpg?fit=crop&amp;crop=faces%2Centropy&amp;arh=2&amp;w=1080&amp;fm=jpg&amp;s=6207518b723ea16136e1f15702c176ba", "width": 1080, "height": 720}], "variants": {}, "id": "oRu4Q291bgQNhUc6ls4SMPSQ2M2JmsFAltPq3jl9Mik"}], "enabled": false}, "thumbnail": "https://b.thumbs.redditmedia.com/MzXG5lNvsJ2TBOdSXa_dXw1d3tw34Haqry-cFI9fPjc.jpg", "edited": false, "link_flair_css_class": null, "author_flair_css_class": "noob", "contest_mode": false, "gilded": 0, "downs": 0, "brand_safe": true, "secure_media_embed": {}, "media_embed": {}, "post_hint": "link", "author_flair_text": "redditor for 3 months", "stickied": false, "visited": false, "can_gild": false, "thumbnail_height": 93, "parent_whitelist_status": "all_ads", "name": "t3_84yvbe", "spoiler": false, "permalink": "/r/Bitcoin/comments/84yvbe/google_and_facebook_banning_cryptocurrency_ads/", "subreddit_type": "public", "locked": false, "hide_score": false, "created": 1521263482.0, "url": "https://www.thestreet.com/story/14525560/1/google-facebook-ban-cryptocurrency-ads-may-be-good-for-bitcoin.html", "whitelist_status": "all_ads", "quarantine": false, "subreddit_subscribers": 772141, "created_utc": 1521234682.0, "subreddit_name_prefixed": "r/Bitcoin", "ups": 208, "media": null, "num_comments": 44, "is_self": false, "title": "Google and Facebook banning cryptocurrency ads may actually be good for Bitcoin", "mod_note": null, "is_video": false, "distinguished": null}}, {"kind": "t3", "data": {"subreddit_id": "t5_2s3qj", "approved_at_utc": null, "send_replies": true, "mod_reason_by": null, "banned_by": null, "num_reports": null, "removal_reason": null, "thumbnail_width": null, "subreddit": "Bitcoin", "selftext_html": "&lt;!-- SC_OFF --&gt;&lt;div class=\"md\"&gt;&lt;p&gt;Fake emails telling users that they couldn\u2019t use PayPal for cryptocurrency trading were sent to many PayPal users.&lt;/p&gt;\n\n&lt;p&gt;On March 16th 2018, these phishing emails were sent to many cryptocurrency users. These emails claim that trading cryptocurrencies is prohibited under PayPal\u2019s Acceptable Use Policy, and ask the user to stop using PayPal for cryptocurrencies.&lt;/p&gt;\n\n&lt;p&gt;&lt;a href=\"https://stopthefud.wordpress.com/2018/03/16/alert-paypal-phishing/\"&gt;https://stopthefud.wordpress.com/2018/03/16/alert-paypal-phishing/&lt;/a&gt;&lt;/p&gt;\n\n&lt;p&gt;(Reddit wouldn&amp;#39;t let me submit this as a link)&lt;/p&gt;\n&lt;/div&gt;&lt;!-- SC_ON --&gt;", "selftext": "Fake emails telling users that they couldn\u2019t use PayPal for cryptocurrency trading were sent to many PayPal users.\n\nOn March 16th 2018, these phishing emails were sent to many cryptocurrency users. These emails claim that trading cryptocurrencies is prohibited under PayPal\u2019s Acceptable Use Policy, and ask the user to stop using PayPal for cryptocurrencies.\n\nhttps://stopthefud.wordpress.com/2018/03/16/alert-paypal-phishing/\n\n(Reddit wouldn't let me submit this as a link)", "likes": null, "suggested_sort": null, "user_reports": [], "secure_media": null, "is_reddit_media_domain": false, "saved": false, "id": "854eo4", "banned_at_utc": null, "mod_reason_title": null, "view_count": null, "archived": false, "clicked": false, "no_follow": false, "author": "trontonian", "num_crossposts": 0, "link_flair_text": null, "mod_reports": [], "can_mod_post": false, "is_crosspostable": false, "pinned": false, "score": 8, "approved_by": null, "over_18": false, "report_reasons": null, "domain": "self.Bitcoin", "hidden": false, "preview": {"images": [{"source": {"url": "https://i.redditmedia.com/StBn9PfuKodnApWcPZRH71mRPeAZLyOj9MYvxbiAzKk.jpg?fm=jpg&amp;s=3e41dc77ac09f52656d3b1da278124b6", "width": 1200, "height": 675}, "resolutions": [{"url": "https://i.redditmedia.com/StBn9PfuKodnApWcPZRH71mRPeAZLyOj9MYvxbiAzKk.jpg?fit=crop&amp;crop=faces%2Centropy&amp;arh=2&amp;w=108&amp;fm=jpg&amp;s=91968f20fe5b402679b22aeb09366ead", "width": 108, "height": 60}, {"url": "https://i.redditmedia.com/StBn9PfuKodnApWcPZRH71mRPeAZLyOj9MYvxbiAzKk.jpg?fit=crop&amp;crop=faces%2Centropy&amp;arh=2&amp;w=216&amp;fm=jpg&amp;s=af0ca0fd6b0a558164a9c1b4af8e5220", "width": 216, "height": 121}, {"url": "https://i.redditmedia.com/StBn9PfuKodnApWcPZRH71mRPeAZLyOj9MYvxbiAzKk.jpg?fit=crop&amp;crop=faces%2Centropy&amp;arh=2&amp;w=320&amp;fm=jpg&amp;s=8b7300bc3a66cea34b74ec219c5e62e4", "width": 320, "height": 180}, {"url": "https://i.redditmedia.com/StBn9PfuKodnApWcPZRH71mRPeAZLyOj9MYvxbiAzKk.jpg?fit=crop&amp;crop=faces%2Centropy&amp;arh=2&amp;w=640&amp;fm=jpg&amp;s=42a130e84100aed1f8be8a660e96abe2", "width": 640, "height": 360}, {"url": "https://i.redditmedia.com/StBn9PfuKodnApWcPZRH71mRPeAZLyOj9MYvxbiAzKk.jpg?fit=crop&amp;crop=faces%2Centropy&amp;arh=2&amp;w=960&amp;fm=jpg&amp;s=14d07bc4d37456fe011a782ac082248c", "width": 960, "height": 540}, {"url": "https://i.redditmedia.com/StBn9PfuKodnApWcPZRH71mRPeAZLyOj9MYvxbiAzKk.jpg?fit=crop&amp;crop=faces%2Centropy&amp;arh=2&amp;w=1080&amp;fm=jpg&amp;s=97a2ec967c79fa0c3c0a89a7f1c8a99a", "width": 1080, "height": 607}], "variants": {}, "id": "VRgc8B8cuB6Z3t_kBJxf9goeb457w9YkdaBBlCU_GuA"}], "enabled": false}, "thumbnail": "self", "edited": false, "link_flair_css_class": null, "author_flair_css_class": null, "contest_mode": false, "gilded": 0, "downs": 0, "brand_safe": true, "secure_media_embed": {}, "media_embed": {}, "post_hint": "self", "author_flair_text": null, "stickied": false, "visited": false, "can_gild": false, "thumbnail_height": null, "parent_whitelist_status": "all_ads", "name": "t3_854eo4", "spoiler": false, "permalink": "/r/Bitcoin/comments/854eo4/paypals_warning_email_to_stop_trading_crypto_has/", "subreddit_type": "public", "locked": false, "hide_score": true, "created": 1521329219.0, "url": "https://www.reddit.com/r/Bitcoin/comments/854eo4/paypals_warning_email_to_stop_trading_crypto_has/", "whitelist_status": "all_ads", "quarantine": false, "subreddit_subscribers": 772141, "created_utc": 1521300419.0, "subreddit_name_prefixed": "r/Bitcoin", "ups": 8, "media": null, "num_comments": 2, "is_self": true, "title": "Paypal's Warning Email To Stop Trading Crypto Has Been Proven To Be Fake.", "mod_note": null, "is_video": false, "distinguished": null}}, {"kind": "t3", "data": {"subreddit_id": "t5_2s3qj", "approved_at_utc": null, "send_replies": true, "mod_reason_by": null, "banned_by": null, "num_reports": null, "removal_reason": null, "thumbnail_width": null, "subreddit": "Bitcoin", "selftext_html": null, "selftext": "", "likes": null, "suggested_sort": null, "user_reports": [], "secure_media": null, "is_reddit_media_domain": false, "saved": false, "id": "8532p2", "banned_at_utc": null, "mod_reason_title": null, "view_count": null, "archived": false, "clicked": false, "no_follow": false, "author": "Bitcoin-Yoda", "num_crossposts": 0, "link_flair_text": null, "mod_reports": [], "can_mod_post": false, "is_crosspostable": false, "pinned": false, "score": 17, "approved_by": null, "over_18": false, "report_reasons": null, "domain": "np.reddit.com", "hidden": false, "thumbnail": "default", "edited": false, "link_flair_css_class": null, "author_flair_css_class": null, "contest_mode": false, "gilded": 0, "downs": 0, "brand_safe": true, "secure_media_embed": {}, "media_embed": {}, "author_flair_text": null, "stickied": false, "visited": false, "can_gild": false, "thumbnail_height": null, "parent_whitelist_status": "all_ads", "name": "t3_8532p2", "spoiler": false, "permalink": "/r/Bitcoin/comments/8532p2/please_put_again_the_bitcoin_faq_sticky_post_or/", "subreddit_type": "public", "locked": false, "hide_score": false, "created": 1521313348.0, "url": "https://np.reddit.com/r/BitcoinWiki/wiki/rbitcoin_sticky", "whitelist_status": "all_ads", "quarantine": false, "subreddit_subscribers": 772141, "created_utc": 1521284548.0, "subreddit_name_prefixed": "r/Bitcoin", "ups": 17, "media": null, "num_comments": 2, "is_self": false, "title": "Please put again the Bitcoin FAQ sticky post, or at least a direct link on the side panel. This is an amazing resource for noobs!", "mod_note": null, "is_video": false, "distinguished": null}}, {"kind": "t3", "data": {"subreddit_id": "t5_2s3qj", "approved_at_utc": null, "send_replies": true, "mod_reason_by": null, "banned_by": null, "num_reports": null, "removal_reason": null, "thumbnail_width": 140, "subreddit": "Bitcoin", "selftext_html": null, "selftext": "", "likes": null, "suggested_sort": null, "user_reports": [], "secure_media": {"oembed": {"provider_url": "https://www.youtube.com/", "version": "1.0", "title": "Cryptocurrency and Bitcoin Is Boring, Which Means It Might Finally Be Useful", "type": "video", "author_name": "The right trader", "height": 338, "width": 600, "html": "&lt;iframe width=\"600\" height=\"338\" src=\"https://www.youtube.com/embed/CZsMzMXFxPg?feature=oembed&amp;enablejsapi=1&amp;enablejsapi=1&amp;enablejsapi=1\" frameborder=\"0\" allow=\"autoplay; encrypted-media\" allowfullscreen&gt;&lt;/iframe&gt;", "thumbnail_width": 480, "thumbnail_height": 360, "thumbnail_url": "https://i.ytimg.com/vi/CZsMzMXFxPg/hqdefault.jpg", "provider_name": "YouTube", "author_url": "https://www.youtube.com/channel/UCkgnzEOMcYksK5ChUHmbYow"}, "type": "youtube.com"}, "is_reddit_media_domain": false, "saved": false, "id": "853d3q", "banned_at_utc": null, "mod_reason_title": null, "view_count": null, "archived": false, "clicked": false, "no_follow": false, "author": "cryptowallstreet", "num_crossposts": 0, "link_flair_text": null, "mod_reports": [], "can_mod_post": false, "is_crosspostable": false, "pinned": false, "score": 12, "approved_by": null, "over_18": false, "report_reasons": null, "domain": "youtube.com", "hidden": false, "preview": {"images": [{"source": {"url": "https://i.redditmedia.com/tvkpVyjmimxnXMdo3bkkkDT3XNOOi73n9t1VlAaFiQc.jpg?fm=jpg&amp;s=f46f8cb2c3b33b96afaf06bada0840e6", "width": 480, "height": 360}, "resolutions": [{"url": "https://i.redditmedia.com/tvkpVyjmimxnXMdo3bkkkDT3XNOOi73n9t1VlAaFiQc.jpg?fit=crop&amp;crop=faces%2Centropy&amp;arh=2&amp;w=108&amp;fm=jpg&amp;s=75c4b01de06da855910a99b3d930ec02", "width": 108, "height": 81}, {"url": "https://i.redditmedia.com/tvkpVyjmimxnXMdo3bkkkDT3XNOOi73n9t1VlAaFiQc.jpg?fit=crop&amp;crop=faces%2Centropy&amp;arh=2&amp;w=216&amp;fm=jpg&amp;s=648d133414417f05ca9759966522d1dc", "width": 216, "height": 162}, {"url": "https://i.redditmedia.com/tvkpVyjmimxnXMdo3bkkkDT3XNOOi73n9t1VlAaFiQc.jpg?fit=crop&amp;crop=faces%2Centropy&amp;arh=2&amp;w=320&amp;fm=jpg&amp;s=b2452d5f1e4ff8f49c0f19602527f9cb", "width": 320, "height": 240}], "variants": {}, "id": "wDz4QnHxWh9lekzRU9NW0w2jYqOrbjE-ofXhbyrbu9U"}], "enabled": false}, "thumbnail": "https://b.thumbs.redditmedia.com/1cait-C-UztV6hyjo3J60gh2Pts6GiMiZzkdHgv2_AY.jpg", "edited": false, "link_flair_css_class": null, "author_flair_css_class": null, "contest_mode": false, "gilded": 0, "downs": 0, "brand_safe": true, "secure_media_embed": {"content": "&lt;iframe width=\"600\" height=\"338\" src=\"https://www.youtube.com/embed/CZsMzMXFxPg?feature=oembed&amp;enablejsapi=1&amp;enablejsapi=1&amp;enablejsapi=1\" frameborder=\"0\" allow=\"autoplay; encrypted-media\" allowfullscreen&gt;&lt;/iframe&gt;", "width": 600, "scrolling": false, "media_domain_url": "https://www.redditmedia.com/mediaembed/853d3q", "height": 338}, "media_embed": {"content": "&lt;iframe width=\"600\" height=\"338\" src=\"https://www.youtube.com/embed/CZsMzMXFxPg?feature=oembed&amp;enablejsapi=1&amp;enablejsapi=1&amp;enablejsapi=1\" frameborder=\"0\" allow=\"autoplay; encrypted-media\" allowfullscreen&gt;&lt;/iframe&gt;", "width": 600, "scrolling": false, "media_domain_url": "https://www.redditmedia.com/mediaembed/853d3q", "height": 338}, "post_hint": "rich:video", "author_flair_text": null, "stickied": false, "visited": false, "can_gild": false, "thumbnail_height": 105, "parent_whitelist_status": "all_ads", "name": "t3_853d3q", "spoiler": false, "permalink": "/r/Bitcoin/comments/853d3q/bitcoin_is_boring_which_means_it_might_finally_be/", "subreddit_type": "public", "locked": false, "hide_score": false, "created": 1521317596.0, "url": "https://www.youtube.com/watch?v=CZsMzMXFxPg&amp;feature=youtu.be", "whitelist_status": "all_ads", "quarantine": false, "subreddit_subscribers": 772141, "created_utc": 1521288796.0, "subreddit_name_prefixed": "r/Bitcoin", "ups": 12, "media": {"oembed": {"provider_url": "https://www.youtube.com/", "version": "1.0", "title": "Cryptocurrency and Bitcoin Is Boring, Which Means It Might Finally Be Useful", "type": "video", "author_name": "The right trader", "height": 338, "width": 600, "html": "&lt;iframe width=\"600\" height=\"338\" src=\"https://www.youtube.com/embed/CZsMzMXFxPg?feature=oembed&amp;enablejsapi=1&amp;enablejsapi=1&amp;enablejsapi=1\" frameborder=\"0\" allow=\"autoplay; encrypted-media\" allowfullscreen&gt;&lt;/iframe&gt;", "thumbnail_width": 480, "thumbnail_height": 360, "thumbnail_url": "https://i.ytimg.com/vi/CZsMzMXFxPg/hqdefault.jpg", "provider_name": "YouTube", "author_url": "https://www.youtube.com/channel/UCkgnzEOMcYksK5ChUHmbYow"}, "type": "youtube.com"}, "num_comments": 1, "is_self": false, "title": "Bitcoin Is Boring, Which Means It Might Finally Be Useful?", "mod_note": null, "is_video": false, "distinguished": null}}, {"kind": "t3", "data": {"subreddit_id": "t5_2s3qj", "approved_at_utc": null, "send_replies": true, "mod_reason_by": null, "banned_by": null, "num_reports": null, "removal_reason": null, "thumbnail_width": null, "subreddit": "Bitcoin", "selftext_html": "&lt;!-- SC_OFF --&gt;&lt;div class=\"md\"&gt;&lt;p&gt;I usually do 10% of checking account per week but dang I want to do more now that its cheap again..but will stay disciplined I guess. &lt;/p&gt;\n&lt;/div&gt;&lt;!-- SC_ON --&gt;", "selftext": "I usually do 10% of checking account per week but dang I want to do more now that its cheap again..but will stay disciplined I guess. ", "likes": null, "suggested_sort": null, "user_reports": [], "secure_media": null, "is_reddit_media_domain": false, "saved": false, "id": "8532ah", "banned_at_utc": null, "mod_reason_title": null, "view_count": null, "archived": false, "clicked": false, "no_follow": false, "author": "bluethunder1985", "num_crossposts": 0, "link_flair_text": null, "mod_reports": [], "can_mod_post": false, "is_crosspostable": false, "pinned": false, "score": 17, "approved_by": null, "over_18": false, "report_reasons": null, "domain": "self.Bitcoin", "hidden": false, "thumbnail": "self", "edited": false, "link_flair_css_class": null, "author_flair_css_class": null, "contest_mode": false, "gilded": 0, "downs": 0, "brand_safe": true, "secure_media_embed": {}, "media_embed": {}, "author_flair_text": null, "stickied": false, "visited": false, "can_gild": false, "thumbnail_height": null, "parent_whitelist_status": "all_ads", "name": "t3_8532ah", "spoiler": false, "permalink": "/r/Bitcoin/comments/8532ah/anyone_else_trying_to_justify_buying_more_than/", "subreddit_type": "public", "locked": false, "hide_score": false, "created": 1521313192.0, "url": "https://www.reddit.com/r/Bitcoin/comments/8532ah/anyone_else_trying_to_justify_buying_more_than/", "whitelist_status": "all_ads", "quarantine": false, "subreddit_subscribers": 772141, "created_utc": 1521284392.0, "subreddit_name_prefixed": "r/Bitcoin", "ups": 17, "media": null, "num_comments": 24, "is_self": true, "title": "Anyone else trying to justify buying more than their usual plan?", "mod_note": null, "is_video": false, "distinguished": null}}, {"kind": "t3", "data": {"subreddit_id": "t5_2s3qj", "approved_at_utc": null, "send_replies": true, "mod_reason_by": null, "banned_by": null, "num_reports": null, "removal_reason": null, "thumbnail_width": null, "subreddit": "Bitcoin", "selftext_html": "&lt;!-- SC_OFF --&gt;&lt;div class=\"md\"&gt;&lt;p&gt;\u201cAccording to all known laws of economy, there is no way that a bitcoin should be able to thrive . Its ideas are too advanced and fair to be successful. Bitcoin, of course, flies to the moon. Because Bitcoin don&amp;#39;t care what irrelevant &amp;quot;experts&amp;quot; think is impossible.\u201d LOL\n&lt;a href=\"https://twitter.com/CryptoHebrew/status/974888066577043456\"&gt;https://twitter.com/CryptoHebrew/status/974888066577043456&lt;/a&gt;&lt;/p&gt;\n&lt;/div&gt;&lt;!-- SC_ON --&gt;", "selftext": "\u201cAccording to all known laws of economy, there is no way that a bitcoin should be able to thrive . Its ideas are too advanced and fair to be successful. Bitcoin, of course, flies to the moon. Because Bitcoin don't care what irrelevant \"experts\" think is impossible.\u201d LOL\nhttps://twitter.com/CryptoHebrew/status/974888066577043456\n", "likes": null, "suggested_sort": null, "user_reports": [], "secure_media": null, "is_reddit_media_domain": false, "saved": false, "id": "852r9t", "banned_at_utc": null, "mod_reason_title": null, "view_count": null, "archived": false, "clicked": false, "no_follow": false, "author": "Bit74", "num_crossposts": 0, "link_flair_text": null, "mod_reports": [], "can_mod_post": false, "is_crosspostable": false, "pinned": false, "score": 18, "approved_by": null, "over_18": false, "report_reasons": null, "domain": "self.Bitcoin", "hidden": false, "preview": {"images": [{"source": {"url": "https://i.redditmedia.com/SYnbqS1uPLD3GjRuwccEiZw0FA2R8f4SnW2DUAzkMFk.jpg?fm=jpg&amp;s=523e6c50e7df97f24e8c6c8e077a8e30", "width": 330, "height": 330}, "resolutions": [{"url": "https://i.redditmedia.com/SYnbqS1uPLD3GjRuwccEiZw0FA2R8f4SnW2DUAzkMFk.jpg?fit=crop&amp;crop=faces%2Centropy&amp;arh=2&amp;w=108&amp;fm=jpg&amp;s=6a51c6b945a09ba065b2fd8970d29bc4", "width": 108, "height": 108}, {"url": "https://i.redditmedia.com/SYnbqS1uPLD3GjRuwccEiZw0FA2R8f4SnW2DUAzkMFk.jpg?fit=crop&amp;crop=faces%2Centropy&amp;arh=2&amp;w=216&amp;fm=jpg&amp;s=469fe2d07b53116a5158dc5611ce5725", "width": 216, "height": 216}, {"url": "https://i.redditmedia.com/SYnbqS1uPLD3GjRuwccEiZw0FA2R8f4SnW2DUAzkMFk.jpg?fit=crop&amp;crop=faces%2Centropy&amp;arh=2&amp;w=320&amp;fm=jpg&amp;s=2f71d3d9bf7d38f03e80fc73df0928d7", "width": 320, "height": 320}], "variants": {}, "id": "PG7iGyZYllDYon8Es71JEz2HNFkWbq-I9hMbEke6iNI"}], "enabled": false}, "thumbnail": "self", "edited": false, "link_flair_css_class": null, "author_flair_css_class": "noob", "contest_mode": false, "gilded": 0, "downs": 0, "brand_safe": true, "secure_media_embed": {}, "media_embed": {}, "post_hint": "self", "author_flair_text": "redditor for 3 months", "stickied": false, "visited": false, "can_gild": false, "thumbnail_height": null, "parent_whitelist_status": "all_ads", "name": "t3_852r9t", "spoiler": false, "permalink": "/r/Bitcoin/comments/852r9t/according_to_all_known_laws_of_economy_there_is/", "subreddit_type": "public", "locked": false, "hide_score": false, "created": 1521308139.0, "url": "https://www.reddit.com/r/Bitcoin/comments/852r9t/according_to_all_known_laws_of_economy_there_is/", "whitelist_status": "all_ads", "quarantine": false, "subreddit_subscribers": 772141, "created_utc": 1521279339.0, "subreddit_name_prefixed": "r/Bitcoin", "ups": 18, "media": null, "num_comments": 7, "is_self": true, "title": "\u201cAccording to all known laws of economy, there is no way...\"", "mod_note": null, "is_video": false, "distinguished": null}}, {"kind": "t3", "data": {"subreddit_id": "t5_2s3qj", "approved_at_utc": null, "send_replies": false, "mod_reason_by": null, "banned_by": null, "num_reports": null, "removal_reason": null, "thumbnail_width": null, "subreddit": "Bitcoin", "selftext_html": "&lt;!-- SC_OFF --&gt;&lt;div class=\"md\"&gt;&lt;p&gt;Hi, I was wondering, what are the incentives for creating my own Lightning Node, eg on a Raspberry Pi, if that&amp;#39;s possible?\nI read that a node owner has to pay his own electricity costs of course and then also has to pay some Bitcoin fees when opening or closing channels. In turn I also read that LN doesn&amp;#39;t really generate any significant fees.\nSo before I operate my own LN node I&amp;#39;d like to make sure I&amp;#39;m not actually burning money by doing so.\nThanks for your understanding and help.&lt;/p&gt;\n&lt;/div&gt;&lt;!-- SC_ON --&gt;", "selftext": "Hi, I was wondering, what are the incentives for creating my own Lightning Node, eg on a Raspberry Pi, if that's possible?\nI read that a node owner has to pay his own electricity costs of course and then also has to pay some Bitcoin fees when opening or closing channels. In turn I also read that LN doesn't really generate any significant fees.\nSo before I operate my own LN node I'd like to make sure I'm not actually burning money by doing so.\nThanks for your understanding and help.", "likes": null, "suggested_sort": null, "user_reports": [], "secure_media": null, "is_reddit_media_domain": false, "saved": false, "id": "853kir", "banned_at_utc": null, "mod_reason_title": null, "view_count": null, "archived": false, "clicked": false, "no_follow": false, "author": "Rakhom", "num_crossposts": 0, "link_flair_text": null, "mod_reports": [], "can_mod_post": false, "is_crosspostable": false, "pinned": false, "score": 11, "approved_by": null, "over_18": false, "report_reasons": null, "domain": "self.Bitcoin", "hidden": false, "thumbnail": "self", "edited": false, "link_flair_css_class": null, "author_flair_css_class": null, "contest_mode": false, "gilded": 0, "downs": 0, "brand_safe": true, "secure_media_embed": {}, "media_embed": {}, "author_flair_text": null, "stickied": false, "visited": false, "can_gild": false, "thumbnail_height": null, "parent_whitelist_status": "all_ads", "name": "t3_853kir", "spoiler": false, "permalink": "/r/Bitcoin/comments/853kir/question_about_creating_own_lightning_node/", "subreddit_type": "public", "locked": false, "hide_score": false, "created": 1521320322.0, "url": "https://www.reddit.com/r/Bitcoin/comments/853kir/question_about_creating_own_lightning_node/", "whitelist_status": "all_ads", "quarantine": false, "subreddit_subscribers": 772141, "created_utc": 1521291522.0, "subreddit_name_prefixed": "r/Bitcoin", "ups": 11, "media": null, "num_comments": 9, "is_self": true, "title": "Question about creating own Lightning Node", "mod_note": null, "is_video": false, "distinguished": null}}, {"kind": "t3", "data": {"subreddit_id": "t5_2s3qj", "approved_at_utc": null, "send_replies": true, "mod_reason_by": null, "banned_by": null, "num_reports": null, "removal_reason": null, "thumbnail_width": 140, "subreddit": "Bitcoin", "selftext_html": null, "selftext": "", "likes": null, "suggested_sort": null, "user_reports": [], "secure_media": null, "is_reddit_media_domain": false, "saved": false, "id": "8515i1", "banned_at_utc": null, "mod_reason_title": null, "view_count": null, "archived": false, "clicked": false, "no_follow": false, "author": "woldtrinabd", "num_crossposts": 0, "link_flair_text": null, "mod_reports": [], "can_mod_post": false, "is_crosspostable": false, "pinned": false, "score": 51, "approved_by": null, "over_18": false, "report_reasons": null, "domain": "twitter.com", "hidden": false, "preview": {"images": [{"source": {"url": "https://i.redditmedia.com/9RVXSh0YGuMF92YFSCXwtDbPD7DsYeKg57r8bnXvTcA.jpg?fm=jpg&amp;s=ad91f853256e4c2703b018d02a49ca42", "width": 400, "height": 400}, "resolutions": [{"url": "https://i.redditmedia.com/9RVXSh0YGuMF92YFSCXwtDbPD7DsYeKg57r8bnXvTcA.jpg?fit=crop&amp;crop=faces%2Centropy&amp;arh=2&amp;w=108&amp;fm=jpg&amp;s=b60b65879e9a87c43b8a3930785ec53e", "width": 108, "height": 108}, {"url": "https://i.redditmedia.com/9RVXSh0YGuMF92YFSCXwtDbPD7DsYeKg57r8bnXvTcA.jpg?fit=crop&amp;crop=faces%2Centropy&amp;arh=2&amp;w=216&amp;fm=jpg&amp;s=49d847cd2fed4545e1af1c86e27e26cf", "width": 216, "height": 216}, {"url": "https://i.redditmedia.com/9RVXSh0YGuMF92YFSCXwtDbPD7DsYeKg57r8bnXvTcA.jpg?fit=crop&amp;crop=faces%2Centropy&amp;arh=2&amp;w=320&amp;fm=jpg&amp;s=39b8f696593aa4fe1ca34d4f5df92457", "width": 320, "height": 320}], "variants": {}, "id": "eMaYGtdpCAE4gxqvb4oquc1Yc2k9kqYEtcaRuTj8nHw"}], "enabled": false}, "thumbnail": "https://b.thumbs.redditmedia.com/T3782jDKROFgl1BXFp5-P_ndxVEDUmLzWqwXidGUPNo.jpg", "edited": false, "link_flair_css_class": null, "author_flair_css_class": null, "contest_mode": false, "gilded": 0, "downs": 0, "brand_safe": true, "secure_media_embed": {}, "media_embed": {}, "post_hint": "link", "author_flair_text": null, "stickied": false, "visited": false, "can_gild": false, "thumbnail_height": 140, "parent_whitelist_status": "all_ads", "name": "t3_8515i1", "spoiler": false, "permalink": "/r/Bitcoin/comments/8515i1/breaking_news_according_to_the_latest_reports/", "subreddit_type": "public", "locked": false, "hide_score": false, "created": 1521285598.0, "url": "https://twitter.com/Altcoins_Dux/status/974847223035969536", "whitelist_status": "all_ads", "quarantine": false, "subreddit_subscribers": 772141, "created_utc": 1521256798.0, "subreddit_name_prefixed": "r/Bitcoin", "ups": 51, "media": null, "num_comments": 6, "is_self": false, "title": "BREAKING NEWS: According to the latest reports, Bitcoin doesn't give a fuck about government regulations and 2000 shitcoins gunning for it!", "mod_note": null, "is_video": false, "distinguished": null}}, {"kind": "t3", "data": {"subreddit_id": "t5_2s3qj", "approved_at_utc": null, "send_replies": true, "mod_reason_by": null, "banned_by": null, "num_reports": null, "removal_reason": null, "thumbnail_width": null, "subreddit": "Bitcoin", "selftext_html": null, "selftext": "", "likes": null, "suggested_sort": null, "user_reports": [], "secure_media": null, "is_reddit_media_domain": false, "saved": false, "id": "84yfia", "banned_at_utc": null, "mod_reason_title": null, "view_count": null, "archived": false, "clicked": false, "no_follow": false, "author": "altangent", "num_crossposts": 0, "link_flair_text": null, "mod_reports": [], "can_mod_post": false, "is_crosspostable": false, "pinned": false, "score": 181, "approved_by": null, "over_18": false, "report_reasons": null, "domain": "graph.lndexplorer.com", "hidden": false, "thumbnail": "default", "edited": false, "link_flair_css_class": null, "author_flair_css_class": "noob", "contest_mode": false, "gilded": 0, "downs": 0, "brand_safe": true, "secure_media_embed": {}, "media_embed": {}, "author_flair_text": "redditor for 5 weeks", "stickied": false, "visited": false, "can_gild": false, "thumbnail_height": null, "parent_whitelist_status": "all_ads", "name": "t3_84yfia", "spoiler": false, "permalink": "/r/Bitcoin/comments/84yfia/lightning_network_visualizer_now_live_on_mainnet/", "subreddit_type": "public", "locked": false, "hide_score": false, "created": 1521259982.0, "url": "https://graph.lndexplorer.com/", "whitelist_status": "all_ads", "quarantine": false, "subreddit_subscribers": 772141, "created_utc": 1521231182.0, "subreddit_name_prefixed": "r/Bitcoin", "ups": 181, "media": null, "num_comments": 34, "is_self": false, "title": "Lightning Network visualizer now live on Mainnet", "mod_note": null, "is_video": false, "distinguished": null}}, {"kind": "t3", "data": {"subreddit_id": "t5_2s3qj", "approved_at_utc": null, "send_replies": true, "mod_reason_by": null, "banned_by": null, "num_reports": null, "removal_reason": null, "thumbnail_width": 140, "subreddit": "Bitcoin", "selftext_html": null, "selftext": "", "likes": null, "suggested_sort": null, "user_reports": [], "secure_media": null, "is_reddit_media_domain": false, "saved": false, "id": "84z8ko", "banned_at_utc": null, "mod_reason_title": null, "view_count": null, "archived": false, "clicked": false, "no_follow": false, "author": "MajesticLover", "num_crossposts": 0, "link_flair_text": null, "mod_reports": [], "can_mod_post": false, "is_crosspostable": false, "pinned": false, "score": 110, "approved_by": null, "over_18": false, "report_reasons": null, "domain": "twitter.com", "hidden": false, "preview": {"images": [{"source": {"url": "https://i.redditmedia.com/v5xnf0gwcY1RnIlDlkjkE9hs4vY-ETnBDJSz1WCPivM.jpg?fm=jpg&amp;s=2ac4c1046d17ce3e8d4393a8641f3da8", "width": 1242, "height": 1306}, "resolutions": [{"url": "https://i.redditmedia.com/v5xnf0gwcY1RnIlDlkjkE9hs4vY-ETnBDJSz1WCPivM.jpg?fit=crop&amp;crop=faces%2Centropy&amp;arh=2&amp;w=108&amp;fm=jpg&amp;s=0c74c92dd4da1e88fd172c0a4eb3caf1", "width": 108, "height": 113}, {"url": "https://i.redditmedia.com/v5xnf0gwcY1RnIlDlkjkE9hs4vY-ETnBDJSz1WCPivM.jpg?fit=crop&amp;crop=faces%2Centropy&amp;arh=2&amp;w=216&amp;fm=jpg&amp;s=379ade0c66f576e3ac7e76fef1102f70", "width": 216, "height": 227}, {"url": "https://i.redditmedia.com/v5xnf0gwcY1RnIlDlkjkE9hs4vY-ETnBDJSz1WCPivM.jpg?fit=crop&amp;crop=faces%2Centropy&amp;arh=2&amp;w=320&amp;fm=jpg&amp;s=96f9629db121d572e82a50085187f39e", "width": 320, "height": 336}, {"url": "https://i.redditmedia.com/v5xnf0gwcY1RnIlDlkjkE9hs4vY-ETnBDJSz1WCPivM.jpg?fit=crop&amp;crop=faces%2Centropy&amp;arh=2&amp;w=640&amp;fm=jpg&amp;s=fc86c1589641770e16239c64474fa05b", "width": 640, "height": 672}, {"url": "https://i.redditmedia.com/v5xnf0gwcY1RnIlDlkjkE9hs4vY-ETnBDJSz1WCPivM.jpg?fit=crop&amp;crop=faces%2Centropy&amp;arh=2&amp;w=960&amp;fm=jpg&amp;s=94603ec97e9ebd366081579c860e358a", "width": 960, "height": 1009}, {"url": "https://i.redditmedia.com/v5xnf0gwcY1RnIlDlkjkE9hs4vY-ETnBDJSz1WCPivM.jpg?fit=crop&amp;crop=faces%2Centropy&amp;arh=2&amp;w=1080&amp;fm=jpg&amp;s=06b02ba472a396e6e7d649dea9dc43d7", "width": 1080, "height": 1135}], "variants": {}, "id": "hr8CQaoTnj-QtekY_00BezNAbT7cTBO_f17wyvZijS8"}], "enabled": false}, "thumbnail": "https://b.thumbs.redditmedia.com/feiIFxzODCqAJla4abz6oTYWVgRNOxQGusDwnTfxxKU.jpg", "edited": false, "link_flair_css_class": null, "author_flair_css_class": "noob", "contest_mode": false, "gilded": 0, "downs": 0, "brand_safe": true, "secure_media_embed": {}, "media_embed": {}, "post_hint": "link", "author_flair_text": "redditor for 1 week", "stickied": false, "visited": false, "can_gild": false, "thumbnail_height": 140, "parent_whitelist_status": "all_ads", "name": "t3_84z8ko", "spoiler": false, "permalink": "/r/Bitcoin/comments/84z8ko/visualizing_all_horrific_bitcoin_crashes/", "subreddit_type": "public", "locked": false, "hide_score": false, "created": 1521266648.0, "url": "https://twitter.com/bullishgentlemn/status/974413242591191040", "whitelist_status": "all_ads", "quarantine": false, "subreddit_subscribers": 772141, "created_utc": 1521237848.0, "subreddit_name_prefixed": "r/Bitcoin", "ups": 110, "media": null, "num_comments": 21, "is_self": false, "title": "Visualizing All Horrific bitcoin crashes", "mod_note": null, "is_video": false, "distinguished": null}}, {"kind": "t3", "data": {"subreddit_id": "t5_2s3qj", "approved_at_utc": null, "send_replies": true, "mod_reason_by": null, "banned_by": null, "num_reports": null, "removal_reason": null, "thumbnail_width": null, "subreddit": "Bitcoin", "selftext_html": "&lt;!-- SC_OFF --&gt;&lt;div class=\"md\"&gt;&lt;p&gt;A lot of fringe \u201cinvestors\u201d and \u201cbelievers\u201d are losing interest and hope right now. Maybe they got in unwittingly during the fast march up from 10-20k, who knows.&lt;/p&gt;\n\n&lt;p&gt;The sentiment right now from mainstream types is quickly waning.\nMeanwhile, the groundwork that is currently being laid is FAR greater than even 3 months ago when we were at our all time high.&lt;/p&gt;\n\n&lt;p&gt;Let\u2019s also not forget the active price pegging the futures markets are providing on a DAILY basis to give institutional grade requirements for the inevitable ETFs that may eventually be approved.&lt;/p&gt;\n\n&lt;p&gt;The fact that we are waddling between these prices and hitting even 12,000 with little fanfare leads me to believe the next leg up towards $100,000+ , we will then see some true FOMO.&lt;/p&gt;\n\n&lt;p&gt;Stay strong boys, we are the captains of this ship.&lt;/p&gt;\n&lt;/div&gt;&lt;!-- SC_ON --&gt;", "selftext": "A lot of fringe \u201cinvestors\u201d and \u201cbelievers\u201d are losing interest and hope right now. Maybe they got in unwittingly during the fast march up from 10-20k, who knows.\n\nThe sentiment right now from mainstream types is quickly waning.\nMeanwhile, the groundwork that is currently being laid is FAR greater than even 3 months ago when we were at our all time high.\n\nLet\u2019s also not forget the active price pegging the futures markets are providing on a DAILY basis to give institutional grade requirements for the inevitable ETFs that may eventually be approved.\n\nThe fact that we are waddling between these prices and hitting even 12,000 with little fanfare leads me to believe the next leg up towards $100,000+ , we will then see some true FOMO.\n\nStay strong boys, we are the captains of this ship.\n", "likes": null, "suggested_sort": null, "user_reports": [], "secure_media": null, "is_reddit_media_domain": false, "saved": false, "id": "84wu5q", "banned_at_utc": null, "mod_reason_title": null, "view_count": null, "archived": false, "clicked": false, "no_follow": false, "author": "Romeo_the_Dog", "num_crossposts": 0, "link_flair_text": null, "mod_reports": [], "can_mod_post": false, "is_crosspostable": false, "pinned": false, "score": 255, "approved_by": null, "over_18": false, "report_reasons": null, "domain": "self.Bitcoin", "hidden": false, "thumbnail": "self", "edited": false, "link_flair_css_class": null, "author_flair_css_class": "noob", "contest_mode": false, "gilded": 0, "downs": 0, "brand_safe": true, "secure_media_embed": {}, "media_embed": {}, "author_flair_text": "redditor for 3 months", "stickied": false, "visited": false, "can_gild": false, "thumbnail_height": null, "parent_whitelist_status": "all_ads", "name": "t3_84wu5q", "spoiler": false, "permalink": "/r/Bitcoin/comments/84wu5q/psa_this_is_the_calm_before_the_storm/", "subreddit_type": "public", "locked": false, "hide_score": false, "created": 1521247359.0, "url": "https://www.reddit.com/r/Bitcoin/comments/84wu5q/psa_this_is_the_calm_before_the_storm/", "whitelist_status": "all_ads", "quarantine": false, "subreddit_subscribers": 772141, "created_utc": 1521218559.0, "subreddit_name_prefixed": "r/Bitcoin", "ups": 255, "media": null, "num_comments": 239, "is_self": true, "title": "PSA: This is the calm before the storm.", "mod_note": null, "is_video": false, "distinguished": null}}, {"kind": "t3", "data": {"subreddit_id": "t5_2s3qj", "approved_at_utc": null, "send_replies": false, "mod_reason_by": null, "banned_by": null, "num_reports": null, "removal_reason": null, "thumbnail_width": 140, "subreddit": "Bitcoin", "selftext_html": null, "selftext": "", "likes": null, "suggested_sort": null, "user_reports": [], "secure_media": null, "is_reddit_media_domain": false, "saved": false, "id": "8544gw", "banned_at_utc": null, "mod_reason_title": null, "view_count": null, "archived": false, "clicked": false, "no_follow": false, "author": "FIRSTSfeed", "num_crossposts": 0, "link_flair_text": null, "mod_reports": [], "can_mod_post": false, "is_crosspostable": false, "pinned": false, "score": 4, "approved_by": null, "over_18": false, "report_reasons": null, "domain": "firstsfeed.com", "hidden": false, "preview": {"images": [{"source": {"url": "https://i.redditmedia.com/TBW8XmsWwRpXJ6jAfbq4OLh0SWE8VZIFONC6thpGwac.jpg?fm=jpg&amp;s=72169584d00a70b3c99303e27f65699b", "width": 337, "height": 337}, "resolutions": [{"url": "https://i.redditmedia.com/TBW8XmsWwRpXJ6jAfbq4OLh0SWE8VZIFONC6thpGwac.jpg?fit=crop&amp;crop=faces%2Centropy&amp;arh=2&amp;w=108&amp;fm=jpg&amp;s=34e75219397604a99f71bbad5ca4e785", "width": 108, "height": 108}, {"url": "https://i.redditmedia.com/TBW8XmsWwRpXJ6jAfbq4OLh0SWE8VZIFONC6thpGwac.jpg?fit=crop&amp;crop=faces%2Centropy&amp;arh=2&amp;w=216&amp;fm=jpg&amp;s=12c699bfc5fe800c53666286e000c96d", "width": 216, "height": 216}, {"url": "https://i.redditmedia.com/TBW8XmsWwRpXJ6jAfbq4OLh0SWE8VZIFONC6thpGwac.jpg?fit=crop&amp;crop=faces%2Centropy&amp;arh=2&amp;w=320&amp;fm=jpg&amp;s=07712265bde6baa335107e749f74ea28", "width": 320, "height": 320}], "variants": {}, "id": "RU9y11IJRd2jphLY3PJfWMx8Idb2HIpizx7qB3nHgLg"}], "enabled": false}, "thumbnail": "https://a.thumbs.redditmedia.com/VLUmQLMj7dmGByOmSJ0V0uo7feAeuE7tCmfQin4P8j8.jpg", "edited": false, "link_flair_css_class": null, "author_flair_css_class": "noob", "contest_mode": false, "gilded": 0, "downs": 0, "brand_safe": true, "secure_media_embed": {}, "media_embed": {}, "post_hint": "link", "author_flair_text": "redditor for 1 week", "stickied": false, "visited": false, "can_gild": false, "thumbnail_height": 140, "parent_whitelist_status": "all_ads", "name": "t3_8544gw", "spoiler": false, "permalink": "/r/Bitcoin/comments/8544gw/worlds_first_bitcoin_monument_erected_in/", "subreddit_type": "public", "locked": false, "hide_score": true, "created": 1521326484.0, "url": "https://firstsfeed.com/worlds-first-bitcoin-monument-erected-in-slovenian-city-of-kranj/", "whitelist_status": "all_ads", "quarantine": false, "subreddit_subscribers": 772141, "created_utc": 1521297684.0, "subreddit_name_prefixed": "r/Bitcoin", "ups": 4, "media": null, "num_comments": 0, "is_self": false, "title": "World\u2019s first Bitcoin monument erected in Slovenian city of Kranj", "mod_note": null, "is_video": false, "distinguished": null}}, {"kind": "t3", "data": {"subreddit_id": "t5_2s3qj", "approved_at_utc": null, "send_replies": false, "mod_reason_by": null, "banned_by": null, "num_reports": null, "removal_reason": null, "thumbnail_width": 140, "subreddit": "Bitcoin", "selftext_html": null, "selftext": "", "likes": null, "suggested_sort": null, "user_reports": [], "secure_media": null, "is_reddit_media_domain": false, "saved": false, "id": "84uy6e", "banned_at_utc": null, "mod_reason_title": null, "view_count": null, "archived": false, "clicked": false, "no_follow": false, "author": "Suberg", "num_crossposts": 0, "link_flair_text": null, "mod_reports": [], "can_mod_post": false, "is_crosspostable": false, "pinned": false, "score": 530, "approved_by": null, "over_18": false, "report_reasons": null, "domain": "twitter.com", "hidden": false, "preview": {"images": [{"source": {"url": "https://i.redditmedia.com/EC7l8UoLH02jmqsLrCe9ueTGpkzcjx8nWWOpGmb4hYA.jpg?fm=jpg&amp;s=018a094c290f5f67ea38f82c2605043e", "width": 1200, "height": 900}, "resolutions": [{"url": "https://i.redditmedia.com/EC7l8UoLH02jmqsLrCe9ueTGpkzcjx8nWWOpGmb4hYA.jpg?fit=crop&amp;crop=faces%2Centropy&amp;arh=2&amp;w=108&amp;fm=jpg&amp;s=8fc60c03151b9f3cb6d9fd673d03de3b", "width": 108, "height": 81}, {"url": "https://i.redditmedia.com/EC7l8UoLH02jmqsLrCe9ueTGpkzcjx8nWWOpGmb4hYA.jpg?fit=crop&amp;crop=faces%2Centropy&amp;arh=2&amp;w=216&amp;fm=jpg&amp;s=986fbe83a62587d840c53884d98775af", "width": 216, "height": 162}, {"url": "https://i.redditmedia.com/EC7l8UoLH02jmqsLrCe9ueTGpkzcjx8nWWOpGmb4hYA.jpg?fit=crop&amp;crop=faces%2Centropy&amp;arh=2&amp;w=320&amp;fm=jpg&amp;s=35dd2c5bf6e31485eeaf9e81653b4f9f", "width": 320, "height": 240}, {"url": "https://i.redditmedia.com/EC7l8UoLH02jmqsLrCe9ueTGpkzcjx8nWWOpGmb4hYA.jpg?fit=crop&amp;crop=faces%2Centropy&amp;arh=2&amp;w=640&amp;fm=jpg&amp;s=d9c9cc32708957d21c6ab618eca1e7aa", "width": 640, "height": 480}, {"url": "https://i.redditmedia.com/EC7l8UoLH02jmqsLrCe9ueTGpkzcjx8nWWOpGmb4hYA.jpg?fit=crop&amp;crop=faces%2Centropy&amp;arh=2&amp;w=960&amp;fm=jpg&amp;s=73479cc2b3f435c659a0a1642c83ebeb", "width": 960, "height": 720}, {"url": "https://i.redditmedia.com/EC7l8UoLH02jmqsLrCe9ueTGpkzcjx8nWWOpGmb4hYA.jpg?fit=crop&amp;crop=faces%2Centropy&amp;arh=2&amp;w=1080&amp;fm=jpg&amp;s=7775e18b0c4448bb90aa495ac7e54a8d", "width": 1080, "height": 810}], "variants": {}, "id": "BZBKmDJr3mxqzYpwtg_0O-WbbYOaUtHzuWyYV0iBG90"}], "enabled": false}, "thumbnail": "https://b.thumbs.redditmedia.com/qYf3fdYMacdYjDOzEHccSaTbKJKWXd3uVKbj-KIRBio.jpg", "edited": false, "link_flair_css_class": null, "author_flair_css_class": null, "contest_mode": false, "gilded": 0, "downs": 0, "brand_safe": true, "secure_media_embed": {}, "media_embed": {}, "post_hint": "link", "author_flair_text": null, "stickied": false, "visited": false, "can_gild": false, "thumbnail_height": 105, "parent_whitelist_status": "all_ads", "name": "t3_84uy6e", "spoiler": false, "permalink": "/r/Bitcoin/comments/84uy6e/peter_thiel_bitcoin_is_like_a_hedge_of_sorts/", "subreddit_type": "public", "locked": false, "hide_score": false, "created": 1521231179.0, "url": "https://twitter.com/badgerbitcoin/status/974612038482882560", "whitelist_status": "all_ads", "quarantine": false, "subreddit_subscribers": 772141, "created_utc": 1521202379.0, "subreddit_name_prefixed": "r/Bitcoin", "ups": 530, "media": null, "num_comments": 165, "is_self": false, "title": "Peter Thiel: \"Bitcoin is like a hedge of sorts against the whole world falling apart\"", "mod_note": null, "is_video": false, "distinguished": null}}, {"kind": "t3", "data": {"subreddit_id": "t5_2s3qj", "approved_at_utc": null, "send_replies": true, "mod_reason_by": null, "banned_by": null, "num_reports": null, "removal_reason": null, "thumbnail_width": 140, "subreddit": "Bitcoin", "selftext_html": null, "selftext": "", "likes": null, "suggested_sort": null, "user_reports": [], "secure_media": null, "is_reddit_media_domain": false, "saved": false, "id": "84zhqb", "banned_at_utc": null, "mod_reason_title": null, "view_count": null, "archived": false, "clicked": false, "no_follow": false, "author": "Metabudder", "num_crossposts": 0, "link_flair_text": null, "mod_reports": [], "can_mod_post": false, "is_crosspostable": false, "pinned": false, "score": 76, "approved_by": null, "over_18": false, "report_reasons": null, "domain": "twitter.com", "hidden": false, "preview": {"images": [{"source": {"url": "https://i.redditmedia.com/WyCE-xf6K1m-4l_2b_XHLcgJoQx8PrUxtGnMumr5Smc.jpg?fm=jpg&amp;s=3e2ac8ee04f3db84c81e47914580572a", "width": 240, "height": 240}, "resolutions": [{"url": "https://i.redditmedia.com/WyCE-xf6K1m-4l_2b_XHLcgJoQx8PrUxtGnMumr5Smc.jpg?fit=crop&amp;crop=faces%2Centropy&amp;arh=2&amp;w=108&amp;fm=jpg&amp;s=5275e6b5d7aeab40f295d7451c5da8fe", "width": 108, "height": 108}, {"url": "https://i.redditmedia.com/WyCE-xf6K1m-4l_2b_XHLcgJoQx8PrUxtGnMumr5Smc.jpg?fit=crop&amp;crop=faces%2Centropy&amp;arh=2&amp;w=216&amp;fm=jpg&amp;s=bd1fcedf63b238400af762fb0d61d742", "width": 216, "height": 216}], "variants": {}, "id": "1weG91miSdBW5vndDE5nhtrJW7syt83JzT7WKr7Mb8k"}], "enabled": false}, "thumbnail": "https://b.thumbs.redditmedia.com/SZlo0GZTtH0Jd3tXhfbHtBh7OAEKWA-hONLtvQvAolQ.jpg", "edited": false, "link_flair_css_class": null, "author_flair_css_class": "noob", "contest_mode": false, "gilded": 0, "downs": 0, "brand_safe": true, "secure_media_embed": {}, "media_embed": {}, "post_hint": "link", "author_flair_text": "redditor for 3 months", "stickied": false, "visited": false, "can_gild": false, "thumbnail_height": 140, "parent_whitelist_status": "all_ads", "name": "t3_84zhqb", "spoiler": false, "permalink": "/r/Bitcoin/comments/84zhqb/bitcoin_debit_cards_officially_released_in_europe/", "subreddit_type": "public", "locked": false, "hide_score": false, "created": 1521268833.0, "url": "https://twitter.com/thedailyhodl/status/974765847041290241", "whitelist_status": "all_ads", "quarantine": false, "subreddit_subscribers": 772141, "created_utc": 1521240033.0, "subreddit_name_prefixed": "r/Bitcoin", "ups": 76, "media": null, "num_comments": 20, "is_self": false, "title": "Bitcoin debit cards officially released in Europe, with Asia on the way", "mod_note": null, "is_video": false, "distinguished": null}}], "before": null}